Workbook

Sheet Session Feedback
A1: Respondent ID | B1: Date | C1: Venture Name | D1: Program Tier | E1: Hub | F1: Mentor Name | G1: Overall Rating (1-5) | H1: How useful was this mentor session for your current business priorities? | I1: Actionability of Advice | J1: Follow-Up Requested? | K1: Verbatim Feedback | L1: Flagged (≤3)? | M1: Action Taken | N1: Response Category | O1: Feedback category | P1: Remarks | Q1: Resolved? | R1: Reviewed In Stand-Up? | S1: # How useful was this mentor session for your current business priorities? | T1: # Actionability of Advice | U1: # Follow-Up Requested? | V1: Date (Week)
A2: 115104773879 | B2: 46163 | C2: Rupiya Finnovations Pvt Ltd | D2: Accelerate Core | E2: Ahmedabad | F2: Srinivas Yanamandra | G2: =AVERAGE(S2:T2) -> 4.5 | H2: Very useful | I2: Yes | J2: Yes | K2: The session was good and wanted to connect with him again. | S2: =IF(H2="Extremely useful",5,IF(H2="Very useful",4,IF(H2="Moderately useful",3,IF(H2="Slightly useful",2,IF(H2="Not useful",1))))) -> 4 | T2: =IF(I2="Yes",5,IF(I2="Partly",3,IF(I2="No",1))) -> 5 | U2: =IF(J2="Yes",5,IF(J2="No",1)) -> 5 | V2: =IF(ISBLANK(FeedbackTracker[[#This Row],[Date]]),"",INT(FeedbackTracker[[#This Row],[Date]]-WEEKDAY(FeedbackTracker[[#This Row],[Date]],2)+1)) -> 46160
A3: 115100331078 | B3: 46156 | C3: Tikitoro | D3: Accelerate Core | E3: Chennai | F3: Gaurav Bansal | G3: =AVERAGE(S3:T3) -> 3.5 | H3: Very useful | I3: Partly | J3: Yes | K3: The mentor was good and want to meet him even but will fix the agenda and if he agrees that he will be fit for that then only I need a call with him. | O3: 1st Intro call | S3: =IF(H3="Extremely useful",5,IF(H3="Very useful",4,IF(H3="Moderately useful",3,IF(H3="Slightly useful",2,IF(H3="Not useful",1))))) -> 4 | T3: =IF(I3="Yes",5,IF(I3="Partly",3,IF(I3="No",1))) -> 3 | U3: =IF(J3="Yes",5,IF(J3="No",1)) -> 5 | V3: =IF(ISBLANK(FeedbackTracker[[#This Row],[Date]]),"",INT(FeedbackTracker[[#This Row],[Date]]-WEEKDAY(FeedbackTracker[[#This Row],[Date]],2)+1)) -> 46153
A4: 115101125450 | B4: 46157 | C4: Terrablu | D4: Accelerate Core | E4: Pune | F4: Anant Sood | G4: =AVERAGE(S4:T4) -> 4.5 | H4: Very useful | I4: Yes | J4: Yes | K4: The session was good. The clearity with which Mr. sood was taking session was beyond imagination. | L4: Yes | S4: =IF(H4="Extremely useful",5,IF(H4="Very useful",4,IF(H4="Moderately useful",3,IF(H4="Slightly useful",2,IF(H4="Not useful",1))))) -> 4 | T4: =IF(I4="Yes",5,IF(I4="Partly",3,IF(I4="No",1))) -> 5 | U4: =IF(J4="Yes",5,IF(J4="No",1)) -> 5 | V4: =IF(ISBLANK(FeedbackTracker[[#This Row],[Date]]),"",INT(FeedbackTracker[[#This Row],[Date]]-WEEKDAY(FeedbackTracker[[#This Row],[Date]],2)+1)) -> 46153
A5: 115100263275 | B5: 46156 | C5: Eximburg International | D5: Accelerate Core | E5: Ahmedabad | F5: Kushagra Gupta | G5: =AVERAGE(S5:T5) -> 3.5 | H5: Very useful | I5: Partly | J5: No | K5: The mentor was good but same as mentioned earlier we needed somebody to audit our amazon account. | L5: =IF(G5<=3,"Yes","No") -> No | N5: Received | P5: 14-May-2026: Venture denied for another session with mentor | S5: =IF(H5="Extremely useful",5,IF(H5="Very useful",4,IF(H5="Moderately useful",3,IF(H5="Slightly useful",2,IF(H5="Not useful",1))))) -> 4 | T5: =IF(I5="Yes",5,IF(I5="Partly",3,IF(I5="No",1))) -> 3 | U5: =IF(J5="Yes",5,IF(J5="No",1)) -> 1 | V5: =IF(ISBLANK(FeedbackTracker[[#This Row],[Date]]),"",INT(FeedbackTracker[[#This Row],[Date]]-WEEKDAY(FeedbackTracker[[#This Row],[Date]],2)+1)) -> 46153
A6: 115100253848 | B6: 46156 | C6: Eximburg International | D6: Accelerate Core | E6: Ahmedabad | F6: Sriram Chidambaram | G6: =AVERAGE(S6:T6) -> 4.5 | H6: Very useful | I6: Yes | J6: No | K6: It was meaningful sssion but we want to more sessions about the valuation. | S6: =IF(H6="Extremely useful",5,IF(H6="Very useful",4,IF(H6="Moderately useful",3,IF(H6="Slightly useful",2,IF(H6="Not useful",1))))) -> 4 | T6: =IF(I6="Yes",5,IF(I6="Partly",3,IF(I6="No",1))) -> 5 | U6: =IF(J6="Yes",5,IF(J6="No",1)) -> 1 | V6: =IF(ISBLANK(FeedbackTracker[[#This Row],[Date]]),"",INT(FeedbackTracker[[#This Row],[Date]]-WEEKDAY(FeedbackTracker[[#This Row],[Date]],2)+1)) -> 46153
A7: 115100236156 | B7: 46156 | C7: Zeus Engitech Private Limited | D7: Accelerate Core | E7: Ahmedabad | F7: Ankit Majumdar | G7: =AVERAGE(S7:T7) -> 4 | H7: Moderately useful | I7: Yes | J7: Yes | K7: I selected “Moderately” because I would like to first implement the insights and suggestions shared, and then evaluate how effective they are. Overall, the session was very good. | L7: =IF(G7<=3,"Yes","No") -> No | N7: Received | P7: 13-Apr-2026: The mentor was good, but they wanted to see if the suggestions are truely useful at time of implementation. | S7: =IF(H7="Extremely useful",5,IF(H7="Very useful",4,IF(H7="Moderately useful",3,IF(H7="Slightly useful",2,IF(H7="Not useful",1))))) -> 3 | T7: =IF(I7="Yes",5,IF(I7="Partly",3,IF(I7="No",1))) -> 5 | U7: =IF(J7="Yes",5,IF(J7="No",1)) -> 5 | V7: =IF(ISBLANK(FeedbackTracker[[#This Row],[Date]]),"",INT(FeedbackTracker[[#This Row],[Date]]-WEEKDAY(FeedbackTracker[[#This Row],[Date]],2)+1)) -> 46153
A8: 115099419177 | B8: 46155 | C8: Manufyx | D8: Accelerate Core | E8: Chennai | F8: Sanjay Sharma | G8: =AVERAGE(S8:T8) -> 4.5 | H8: Very useful | I8: Yes | J8: No | K8: The session was very nice and Wadhwani is giving us what we need. | L8: =IF(G8<=3,"Yes","No") -> No | P8: 13-May-2026: Venture denied for another session with mentor | S8: =IF(H8="Extremely useful",5,IF(H8="Very useful",4,IF(H8="Moderately useful",3,IF(H8="Slightly useful",2,IF(H8="Not useful",1))))) -> 4 | T8: =IF(I8="Yes",5,IF(I8="Partly",3,IF(I8="No",1))) -> 5 | U8: =IF(J8="Yes",5,IF(J8="No",1)) -> 1 | V8: =IF(ISBLANK(FeedbackTracker[[#This Row],[Date]]),"",INT(FeedbackTracker[[#This Row],[Date]]-WEEKDAY(FeedbackTracker[[#This Row],[Date]],2)+1)) -> 46153
A9: 115099491986 | B9: 46155 | C9: Sarumam Pharmacy | D9: Accelerate Core | E9: Chennai | F9: Ajay Rungta | G9: =AVERAGE(S9:T9) -> 4.5 | H9: Very useful | I9: Yes | J9: Yes | K9: He was able to identify what I needed and provided the solutions to me immediately. | L9: =IF(G9<=3,"Yes","No") -> No | S9: =IF(H9="Extremely useful",5,IF(H9="Very useful",4,IF(H9="Moderately useful",3,IF(H9="Slightly useful",2,IF(H9="Not useful",1))))) -> 4 | T9: =IF(I9="Yes",5,IF(I9="Partly",3,IF(I9="No",1))) -> 5 | U9: =IF(J9="Yes",5,IF(J9="No",1)) -> 5 | V9: =IF(ISBLANK(FeedbackTracker[[#This Row],[Date]]),"",INT(FeedbackTracker[[#This Row],[Date]]-WEEKDAY(FeedbackTracker[[#This Row],[Date]],2)+1)) -> 46153
A10: 115097528792 | B10: 46153 | C10: REAGRI - NANOBEE BIOINNOVATIONS | D10: Accelerate Core | E10: Ahmedabad | F10: Suhasini Barman | G10: =AVERAGE(S10:T10) -> 4.5 | H10: Very useful | I10: Yes | J10: Yes | K10: The session was very useful. | L10: No | S10: =IF(H10="Extremely useful",5,IF(H10="Very useful",4,IF(H10="Moderately useful",3,IF(H10="Slightly useful",2,IF(H10="Not useful",1))))) -> 4 | T10: =IF(I10="Yes",5,IF(I10="Partly",3,IF(I10="No",1))) -> 5 | U10: =IF(J10="Yes",5,IF(J10="No",1)) -> 5 | V10: =IF(ISBLANK(FeedbackTracker[[#This Row],[Date]]),"",INT(FeedbackTracker[[#This Row],[Date]]-WEEKDAY(FeedbackTracker[[#This Row],[Date]],2)+1)) -> 46153
A11: 115095338090 | B11: 46149 | C11: VideoSDK | D11: Accelerate Core | E11: Ahmedabad | F11: Mithun Kumar Mahendra | G11: =AVERAGE(S11:T11) -> 5 | H11: Extremely useful | I11: Yes | J11: No | K11: The session was very amazing. Wanted to connect to other mentor that is Mr. Sid Pandey. | L11: No | S11: =IF(H11="Extremely useful",5,IF(H11="Very useful",4,IF(H11="Moderately useful",3,IF(H11="Slightly useful",2,IF(H11="Not useful",1))))) -> 5 | T11: =IF(I11="Yes",5,IF(I11="Partly",3,IF(I11="No",1))) -> 5 | U11: =IF(J11="Yes",5,IF(J11="No",1)) -> 1 | V11: =IF(ISBLANK(FeedbackTracker[[#This Row],[Date]]),"",INT(FeedbackTracker[[#This Row],[Date]]-WEEKDAY(FeedbackTracker[[#This Row],[Date]],2)+1)) -> 46146
A12: 115095310455 | B12: 46149 | C12: Leap Info | D12: Accelerate Core | E12: Pune | F12: Dr. Naman Agarwal | G12: =AVERAGE(S12:T12) -> 3 | H12: Moderately useful | I12: Partly | J12: No | K12: I was expecting insights on business opportunities from the Netherlands side, but the discussion was mostly around Indian government startup schemes. | L12: No | M12: Reached out: Response Received | N12: Received | O12: 1st Intro Call | P12: 7-May-2026: The venture shared that they were expecting more discussion around Netherlands-side business opportunities, since the expert was from the Netherlands Embassy. However, they had been connected with Naman specifically for IP and patent-related guidance, and they found the session informative overall. We also checked if they wanted any further mentor connect, but currently they don’t have any additional requirements. | S12: =IF(H12="Extremely useful",5,IF(H12="Very useful",4,IF(H12="Moderately useful",3,IF(H12="Slightly useful",2,IF(H12="Not useful",1))))) -> 3 | T12: =IF(I12="Yes",5,IF(I12="Partly",3,IF(I12="No",1))) -> 3 | U12: =IF(J12="Yes",5,IF(J12="No",1)) -> 1 | V12: =IF(ISBLANK(FeedbackTracker[[#This Row],[Date]]),"",INT(FeedbackTracker[[#This Row],[Date]]-WEEKDAY(FeedbackTracker[[#This Row],[Date]],2)+1)) -> 46146
A13: 115092759158 | B13: 46146 | C13: Svan Autotech | D13: Accelerate Core | E13: Ahmedabad | F13: Sriram Chidambaram | G13: =AVERAGE(S13:T13) -> 5 | H13: Extremely useful | I13: Yes | J13: Yes | K13: We want to take his help in making the financial projections. It will greatly help us close the current round. | L13: No | S13: =IF(H13="Extremely useful",5,IF(H13="Very useful",4,IF(H13="Moderately useful",3,IF(H13="Slightly useful",2,IF(H13="Not useful",1))))) -> 5 | T13: =IF(I13="Yes",5,IF(I13="Partly",3,IF(I13="No",1))) -> 5 | U13: =IF(J13="Yes",5,IF(J13="No",1)) -> 5 | V13: =IF(ISBLANK(FeedbackTracker[[#This Row],[Date]]),"",INT(FeedbackTracker[[#This Row],[Date]]-WEEKDAY(FeedbackTracker[[#This Row],[Date]],2)+1)) -> 46146
A14: 115084318304 | B14: 46134 | C14: Keepsake Automation Pvt Ltd | D14: Accelerate Core | E14: Ahmedabad | F14: Garima Mitra | G14: =AVERAGE(S14:T14) -> 3 | H14: Moderately useful | I14: Partly | J14: No | K14: Mentor offered us paid services for advice and we don't | L14: Yes | M14: Reached out: Response Received | N14: Received | O14: Misalignment | P14: 22-Apr-2026: The services or fees mentioned by Garima are strictly related to legal documentation and other legal matters. The fee has been charged solely for these services, and not for anything else. We also checked the session's transcript and recording, and found that venture got the proper mentoring what was supposed to be given. | S14: =IF(H14="Extremely useful",5,IF(H14="Very useful",4,IF(H14="Moderately useful",3,IF(H14="Slightly useful",2,IF(H14="Not useful",1))))) -> 3 | T14: =IF(I14="Yes",5,IF(I14="Partly",3,IF(I14="No",1))) -> 3 | U14: =IF(J14="Yes",5,IF(J14="No",1)) -> 1 | V14: =IF(ISBLANK(FeedbackTracker[[#This Row],[Date]]),"",INT(FeedbackTracker[[#This Row],[Date]]-WEEKDAY(FeedbackTracker[[#This Row],[Date]],2)+1)) -> 46132
A15: 115084260317 | B15: 46134 | C15: Elite Decor Pvt. Ltd | D15: Accelerate Select | E15: Ahmedabad | F15: Vinod Keni | G15: =AVERAGE(S15:T15) -> 3.5 | H15: Very useful | I15: Partly | J15: Yes | K15: the sesession was good and wanted to have one more follow session with him. | L15: Yes | M15: Reached out: Response Received | N15: Received | O15: 1st Intro Call | P15: 22-Apr-2026: Wanted one more session with mentor | S15: =IF(H15="Extremely useful",5,IF(H15="Very useful",4,IF(H15="Moderately useful",3,IF(H15="Slightly useful",2,IF(H15="Not useful",1))))) -> 4 | T15: =IF(I15="Yes",5,IF(I15="Partly",3,IF(I15="No",1))) -> 3 | U15: =IF(J15="Yes",5,IF(J15="No",1)) -> 5 | V15: =IF(ISBLANK(FeedbackTracker[[#This Row],[Date]]),"",INT(FeedbackTracker[[#This Row],[Date]]-WEEKDAY(FeedbackTracker[[#This Row],[Date]],2)+1)) -> 46132
A16: 115080568744 | B16: 46128.594 | C16: MiCoB Pvt Ltd | D16: Accelerate Core | E16: Ahmedabad | F16: Amit Saluja | G16: =AVERAGE(S16:T16) -> 4 | H16: Extremely useful | I16: Partly | J16: Yes | K16: Want one more session and was very good session. | L16: =IF(G16<=3,"Yes","No") -> No | M16: Reached out: Response Received | O16: 1st Intro Call | P16: 17-04-2026: | S16: =IF(H16="Extremely useful",5,IF(H16="Very useful",4,IF(H16="Moderately useful",3,IF(H16="Slightly useful",2,IF(H16="Not useful",1))))) -> 5 | T16: =IF(I16="Yes",5,IF(I16="Partly",3,IF(I16="No",1))) -> 3 | U16: =IF(J16="Yes",5,IF(J16="No",1)) -> 5 | V16: =IF(ISBLANK(FeedbackTracker[[#This Row],[Date]]),"",INT(FeedbackTracker[[#This Row],[Date]]-WEEKDAY(FeedbackTracker[[#This Row],[Date]],2)+1)) -> 46125
A17: 115080545344 | B17: 46128.568 | C17: Torchit | D17: Accelerate Core | E17: Ahmedabad | F17: Sriram Chidambaram | G17: =AVERAGE(S17:T17) -> 4.5 | H17: Very useful | I17: Yes | J17: No | K17: The session was good and mentor is perfectly fine. | L17: =IF(G17<=3,"Yes","No") -> No | M17: Reached out: Response Received | S17: =IF(H17="Extremely useful",5,IF(H17="Very useful",4,IF(H17="Moderately useful",3,IF(H17="Slightly useful",2,IF(H17="Not useful",1))))) -> 4 | T17: =IF(I17="Yes",5,IF(I17="Partly",3,IF(I17="No",1))) -> 5 | U17: =IF(J17="Yes",5,IF(J17="No",1)) -> 1 | V17: =IF(ISBLANK(FeedbackTracker[[#This Row],[Date]]),"",INT(FeedbackTracker[[#This Row],[Date]]-WEEKDAY(FeedbackTracker[[#This Row],[Date]],2)+1)) -> 46125
A18: 115080527222 | B18: 46128.542 | C18: Bipolar Factory | D18: Accelerate Prime | E18: Chennai | F18: Sriram Chidambaram | G18: =AVERAGE(S18:T18) -> 4.5 | H18: Very useful | I18: Yes | J18: Yes | K18: It was very good session and will tell when we want to get connected again | L18: =IF(G18<=3,"Yes","No") -> No | S18: =IF(H18="Extremely useful",5,IF(H18="Very useful",4,IF(H18="Moderately useful",3,IF(H18="Slightly useful",2,IF(H18="Not useful",1))))) -> 4 | T18: =IF(I18="Yes",5,IF(I18="Partly",3,IF(I18="No",1))) -> 5 | U18: =IF(J18="Yes",5,IF(J18="No",1)) -> 5 | V18: =IF(ISBLANK(FeedbackTracker[[#This Row],[Date]]),"",INT(FeedbackTracker[[#This Row],[Date]]-WEEKDAY(FeedbackTracker[[#This Row],[Date]],2)+1)) -> 46125
A19: 115067302264 | B19: 46107.501 | C19: Tikitoro | D19: Accelerate Core | E19: Chennai | F19: Shridhar N Upadhye | G19: =AVERAGE(S19:T19) -> 5 | H19: Extremely useful | I19: Yes | J19: No | K19: Mr. Krishna Dorai was excellent and gave some great insights and executable action points in the session. It was great connecting with him. | L19: =IF(G19<=3,"Yes","No") -> No | S19: =IF(H19="Extremely useful",5,IF(H19="Very useful",4,IF(H19="Moderately useful",3,IF(H19="Slightly useful",2,IF(H19="Not useful",1))))) -> 5 | T19: =IF(I19="Yes",5,IF(I19="Partly",3,IF(I19="No",1))) -> 5 | U19: =IF(J19="Yes",5,IF(J19="No",1)) -> 1 | V19: =IF(ISBLANK(FeedbackTracker[[#This Row],[Date]]),"",INT(FeedbackTracker[[#This Row],[Date]]-WEEKDAY(FeedbackTracker[[#This Row],[Date]],2)+1)) -> 46104
A20: 115065626399 | B20: 46105.558 | C20: Stembotix | D20: Accelerate Core | E20: Ahmedabad | F20: Amiya Srivastava | G20: =AVERAGE(S20:T20) -> 4.5 | H20: Very useful | I20: Yes | J20: Yes | K20: Want to meet the mentor again in Mid April | L20: =IF(G20<=3,"Yes","No") -> No | M20: Reached out: Response Received | S20: =IF(H20="Extremely useful",5,IF(H20="Very useful",4,IF(H20="Moderately useful",3,IF(H20="Slightly useful",2,IF(H20="Not useful",1))))) -> 4 | T20: =IF(I20="Yes",5,IF(I20="Partly",3,IF(I20="No",1))) -> 5 | U20: =IF(J20="Yes",5,IF(J20="No",1)) -> 5 | V20: =IF(ISBLANK(FeedbackTracker[[#This Row],[Date]]),"",INT(FeedbackTracker[[#This Row],[Date]]-WEEKDAY(FeedbackTracker[[#This Row],[Date]],2)+1)) -> 46104
A21: 115062696710 | B21: 46100.423 | C21: Tikitoro | D21: Accelerate Core | E21: Chennai | F21: Shridhar N Upadhye | G21: =AVERAGE(S21:T21) -> 4.5 | H21: Very useful | I21: Yes | J21: Yes | K21: We discussed on clearity and looking forward to meet with mentor again. | L21: =IF(G21<=3,"Yes","No") -> No | M21: Reached out: Response Received | S21: =IF(H21="Extremely useful",5,IF(H21="Very useful",4,IF(H21="Moderately useful",3,IF(H21="Slightly useful",2,IF(H21="Not useful",1))))) -> 4 | T21: =IF(I21="Yes",5,IF(I21="Partly",3,IF(I21="No",1))) -> 5 | U21: =IF(J21="Yes",5,IF(J21="No",1)) -> 5 | V21: =IF(ISBLANK(FeedbackTracker[[#This Row],[Date]]),"",INT(FeedbackTracker[[#This Row],[Date]]-WEEKDAY(FeedbackTracker[[#This Row],[Date]],2)+1)) -> 46097
A22: 115061950102 | B22: 46099.527 | C22: Bull AgriTech | D22: Accelerate Core | E22: Ahmedabad | F22: Shailendrasinh Rajput | G22: =AVERAGE(S22:T22) -> 3.5 | H22: Very useful | I22: Partly | J22: Yes | K22: Wanted to connected with mentor again, as he is a very good fit for our requirement. | L22: =IF(G22<=3,"Yes","No") -> No | M22: Reached out: Response Received | N22: Received | O22: 1st Intro Call | P22: 18-mar-2026: The venture expected immediate advice, but as it was an introductory call, the mentor focused on understanding the venture first. | S22: =IF(H22="Extremely useful",5,IF(H22="Very useful",4,IF(H22="Moderately useful",3,IF(H22="Slightly useful",2,IF(H22="Not useful",1))))) -> 4 | T22: =IF(I22="Yes",5,IF(I22="Partly",3,IF(I22="No",1))) -> 3 | U22: =IF(J22="Yes",5,IF(J22="No",1)) -> 5 | V22: =IF(ISBLANK(FeedbackTracker[[#This Row],[Date]]),"",INT(FeedbackTracker[[#This Row],[Date]]-WEEKDAY(FeedbackTracker[[#This Row],[Date]],2)+1)) -> 46097
A23: 115060369534 | B23: 46097.433 | C23: Bebe Burp | D23: Accelerate Core | E23: Ahmedabad | F23: Bharat Hudadalli | G23: =AVERAGE(S23:T23) -> 3.5 | H23: Very useful | I23: Partly | J23: Yes | K23: The session gave us a good insight for D2C but moreover he is about to get back to us with a proposal for the service he can offer in 4 days | L23: =IF(G23<=3,"Yes","No") -> No | M23: Reached out: Response Received | N23: Received | O23: 1st Intro Call | P23: 31-mar-2026: It was an intro call that's why mentor didn't gave his feedbacks and venture wants to get connected with mentor again 26-Mar-2026: Not reachable | S23: =IF(H23="Extremely useful",5,IF(H23="Very useful",4,IF(H23="Moderately useful",3,IF(H23="Slightly useful",2,IF(H23="Not useful",1))))) -> 4 | T23: =IF(I23="Yes",5,IF(I23="Partly",3,IF(I23="No",1))) -> 3 | U23: =IF(J23="Yes",5,IF(J23="No",1)) -> 5 | V23: =IF(ISBLANK(FeedbackTracker[[#This Row],[Date]]),"",INT(FeedbackTracker[[#This Row],[Date]]-WEEKDAY(FeedbackTracker[[#This Row],[Date]],2)+1)) -> 46097
A24: 115058872547 | B24: 46094.684 | C24: Aeronero Solutions Private Limited | D24: Accelerate Core | E24: Chennai | F24: Sriram Chidambaram | G24: =AVERAGE(S24:T24) -> 3.5 | H24: Very useful | I24: Partly | J24: No | K24: I want a deep dive in some specific areas | L24: =IF(G24<=3,"Yes","No") -> No | M24: Reached out: Response Received | N24: Received | O24: Misalignment | P24: 13-Mar-2026: Venture found that mentor is suitable for early age startups but not entures like them. The knowledge was at very basic and useful for early age startups | S24: =IF(H24="Extremely useful",5,IF(H24="Very useful",4,IF(H24="Moderately useful",3,IF(H24="Slightly useful",2,IF(H24="Not useful",1))))) -> 4 | T24: =IF(I24="Yes",5,IF(I24="Partly",3,IF(I24="No",1))) -> 3 | U24: =IF(J24="Yes",5,IF(J24="No",1)) -> 1 | V24: =IF(ISBLANK(FeedbackTracker[[#This Row],[Date]]),"",INT(FeedbackTracker[[#This Row],[Date]]-WEEKDAY(FeedbackTracker[[#This Row],[Date]],2)+1)) -> 46090
A25: 115056979250 | B25: 46092.428 | C25: Vaultastic | D25: Accelerate Core | E25: Pune | F25: Deepak Srinivasan | G25: =AVERAGE(S25:T25) -> 3 | H25: Moderately useful | I25: Partly | J25: No | K25: The session was okay and we are looking more detailed for BFSI. | L25: =IF(G25<=3,"Yes","No") -> Yes | N25: Received | O25: Misalignment | P25: 26-Mar-2026: Mr. Srinivasan is an early age startup mentor, we want some mature mentors who can replicate Banking model. Informed Rishabh about this and want mentor for fundraising thing and was conveyed to Rishabh about this. | S25: =IF(H25="Extremely useful",5,IF(H25="Very useful",4,IF(H25="Moderately useful",3,IF(H25="Slightly useful",2,IF(H25="Not useful",1))))) -> 3 | T25: =IF(I25="Yes",5,IF(I25="Partly",3,IF(I25="No",1))) -> 3 | U25: =IF(J25="Yes",5,IF(J25="No",1)) -> 1 | V25: =IF(ISBLANK(FeedbackTracker[[#This Row],[Date]]),"",INT(FeedbackTracker[[#This Row],[Date]]-WEEKDAY(FeedbackTracker[[#This Row],[Date]],2)+1)) -> 46090
A26: 115056976367 | B26: 46092.418 | C26: Bebe Burp | D26: Accelerate Core | E26: Ahmedabad | F26: Bharat Hudadalli | G26: =AVERAGE(S26:T26) -> 4 | H26: Extremely useful | I26: Partly | J26: Yes | K26: Bharat really has great knowledge and want to connect with him again he has knowledge for scaleup thing | L26: =IF(G26<=3,"Yes","No") -> No | M26: Received | N26: Received | O26: 1st Intro Call | P26: 11-Mar-2026: The venture expected immediate advice, but as it was an introductory call, the mentor focused on understanding the venture first. | S26: =IF(H26="Extremely useful",5,IF(H26="Very useful",4,IF(H26="Moderately useful",3,IF(H26="Slightly useful",2,IF(H26="Not useful",1))))) -> 5 | T26: =IF(I26="Yes",5,IF(I26="Partly",3,IF(I26="No",1))) -> 3 | U26: =IF(J26="Yes",5,IF(J26="No",1)) -> 5 | V26: =IF(ISBLANK(FeedbackTracker[[#This Row],[Date]]),"",INT(FeedbackTracker[[#This Row],[Date]]-WEEKDAY(FeedbackTracker[[#This Row],[Date]],2)+1)) -> 46090
A27: 115056975802 | B27: 46092.417 | C27: Bebe Burp | D27: Accelerate Core | E27: Ahmedabad | F27: Sivesh Kumar | G27: =AVERAGE(S27:T27) -> 1.5 | H27: Slightly useful | I27: No | J27: No | K27: The session was bit confusing. | L27: =IF(G27<=3,"Yes","No") -> Yes | M27: No Response: Call Disconnected | N27: Received | O27: Misalignment | P27: 30-Mar-2026: For this only Mr. Sivesh was only suggested by Jigar. Mentor do not know much influencer led content. 26-Mar-2026: Not reachable | S27: =IF(H27="Extremely useful",5,IF(H27="Very useful",4,IF(H27="Moderately useful",3,IF(H27="Slightly useful",2,IF(H27="Not useful",1))))) -> 2 | T27: =IF(I27="Yes",5,IF(I27="Partly",3,IF(I27="No",1))) -> 1 | U27: =IF(J27="Yes",5,IF(J27="No",1)) -> 1 | V27: =IF(ISBLANK(FeedbackTracker[[#This Row],[Date]]),"",INT(FeedbackTracker[[#This Row],[Date]]-WEEKDAY(FeedbackTracker[[#This Row],[Date]],2)+1)) -> 46090
A28: 115056971880 | B28: 46092.408 | C28: Botminds.ai | D28: Accelerate Core | E28: Chennai | F28: Mahesh Natrajan | G28: =AVERAGE(S28:T28) -> 5 | H28: Extremely useful | I28: Yes | J28: No | K28: The feedback was very helpful and would like to meet the mentor in few months | L28: =IF(G28<=3,"Yes","No") -> No | M28: No Response: Call Disconnected | S28: =IF(H28="Extremely useful",5,IF(H28="Very useful",4,IF(H28="Moderately useful",3,IF(H28="Slightly useful",2,IF(H28="Not useful",1))))) -> 5 | T28: =IF(I28="Yes",5,IF(I28="Partly",3,IF(I28="No",1))) -> 5 | U28: =IF(J28="Yes",5,IF(J28="No",1)) -> 1 | V28: =IF(ISBLANK(FeedbackTracker[[#This Row],[Date]]),"",INT(FeedbackTracker[[#This Row],[Date]]-WEEKDAY(FeedbackTracker[[#This Row],[Date]],2)+1)) -> 46090
A29: 115056188745 | B29: 46091.583 | C29: Qarmatek | D29: Accelerate Core | E29: Ahmedabad | F29: Abhay Jajoo | G29: =AVERAGE(S29:T29) -> 1 | H29: Not useful | I29: No | J29: No | K29: Not at all useful | L29: =IF(G29<=3,"Yes","No") -> Yes | N29: No Response: Call Disconnected | P29: 21-Apr-2026: As were not able to reach out to Founder. We used NoteLM to get the meeting output. Added in Notes 31-Mar-2026: Founder asked to call after next week as he is busy in march closing thing 17-mar-2026: Venture rejected the call 16-mar-2026: Venture rejected the call 13-Mar-2026: Wasn't reachbale 11-mar-2026: Venture asked to call tommorow | S29: =IF(H29="Extremely useful",5,IF(H29="Very useful",4,IF(H29="Moderately useful",3,IF(H29="Slightly useful",2,IF(H29="Not useful",1))))) -> 1 | T29: =IF(I29="Yes",5,IF(I29="Partly",3,IF(I29="No",1))) -> 1 | U29: =IF(J29="Yes",5,IF(J29="No",1)) -> 1 | V29: =IF(ISBLANK(FeedbackTracker[[#This Row],[Date]]),"",INT(FeedbackTracker[[#This Row],[Date]]-WEEKDAY(FeedbackTracker[[#This Row],[Date]],2)+1)) -> 46090
A30: 115056187941 | B30: 46091.582 | C30: Qarmatek | D30: Accelerate Core | E30: Ahmedabad | F30: Nirmallya Roy Chowdhury | G30: =AVERAGE(S30:T30) -> 3 | H30: Moderately useful | I30: Partly | J30: Yes | K30: He was going to get back with a questionairre but he hasn't - so if you could speak with him and check out his interest ? i would be glad to speak with him again | L30: =IF(G30<=3,"Yes","No") -> Yes | N30: No Response: Call Disconnected | P30: 31-Mar-2026: Founder asked to call after next week as he is busy in march closing thing 17-mar-2026: Venture rejected the call 16-mar-2026: Venture rejected the call 13-Mar-2026: Wasn't reachbale 11-mar-2026: Venture asked to call tommorow | S30: =IF(H30="Extremely useful",5,IF(H30="Very useful",4,IF(H30="Moderately useful",3,IF(H30="Slightly useful",2,IF(H30="Not useful",1))))) -> 3 | T30: =IF(I30="Yes",5,IF(I30="Partly",3,IF(I30="No",1))) -> 3 | U30: =IF(J30="Yes",5,IF(J30="No",1)) -> 5 | V30: =IF(ISBLANK(FeedbackTracker[[#This Row],[Date]]),"",INT(FeedbackTracker[[#This Row],[Date]]-WEEKDAY(FeedbackTracker[[#This Row],[Date]],2)+1)) -> 46090
A31: 115056187584 | B31: 46091.578 | C31: Qarmatek | D31: Accelerate Core | E31: Ahmedabad | F31: Anant Sood | G31: =AVERAGE(S31:T31) -> 2.5 | H31: Slightly useful | I31: Partly | J31: No | K31: he was supposed to get back but he never did so won't be going forward with him | L31: =IF(G31<=3,"Yes","No") -> Yes | N31: No Response: Call Disconnected | P31: 31-Mar-2026: Founder asked to call after next week as he is busy in march closing thing 17-mar-2026: Venture rejected the call 16-mar-2026: Venture rejected the call 13-Mar-2026: Wasn't reachbale 11-mar-2026: Venture asked to call tommorow | S31: =IF(H31="Extremely useful",5,IF(H31="Very useful",4,IF(H31="Moderately useful",3,IF(H31="Slightly useful",2,IF(H31="Not useful",1))))) -> 2 | T31: =IF(I31="Yes",5,IF(I31="Partly",3,IF(I31="No",1))) -> 3 | U31: =IF(J31="Yes",5,IF(J31="No",1)) -> 1 | V31: =IF(ISBLANK(FeedbackTracker[[#This Row],[Date]]),"",INT(FeedbackTracker[[#This Row],[Date]]-WEEKDAY(FeedbackTracker[[#This Row],[Date]],2)+1)) -> 46090
A32: 115056185661 | B32: 46091.577 | C32: Qarmatek | D32: Accelerate Core | E32: Ahmedabad | F32: Ashesh D Shah | G32: =AVERAGE(S32:T32) -> 5 | H32: Extremely useful | I32: Yes | J32: No | K32: I have already signed up with Ashesh bhai for the next steps | L32: =IF(G32<=3,"Yes","No") -> No | S32: =IF(H32="Extremely useful",5,IF(H32="Very useful",4,IF(H32="Moderately useful",3,IF(H32="Slightly useful",2,IF(H32="Not useful",1))))) -> 5 | T32: =IF(I32="Yes",5,IF(I32="Partly",3,IF(I32="No",1))) -> 5 | U32: =IF(J32="Yes",5,IF(J32="No",1)) -> 1 | V32: =IF(ISBLANK(FeedbackTracker[[#This Row],[Date]]),"",INT(FeedbackTracker[[#This Row],[Date]]-WEEKDAY(FeedbackTracker[[#This Row],[Date]],2)+1)) -> 46090
A33: 115042914743 | B33: 46071.393 | C33: Agriown Farmtech | D33: Accelerate Core | E33: Ahmedabad | F33: Sriram Chidambaram | G33: =AVERAGE(S33:T33) -> 4.5 | H33: Very useful | I33: Yes | J33: No | K33: The experience was very good and very helpful to us | L33: =IF(G33<=3,"Yes","No") -> No | M33: Reached out: Response Received | S33: =IF(H33="Extremely useful",5,IF(H33="Very useful",4,IF(H33="Moderately useful",3,IF(H33="Slightly useful",2,IF(H33="Not useful",1))))) -> 4 | T33: =IF(I33="Yes",5,IF(I33="Partly",3,IF(I33="No",1))) -> 5 | U33: =IF(J33="Yes",5,IF(J33="No",1)) -> 1 | V33: =IF(ISBLANK(FeedbackTracker[[#This Row],[Date]]),"",INT(FeedbackTracker[[#This Row],[Date]]-WEEKDAY(FeedbackTracker[[#This Row],[Date]],2)+1)) -> 46069
A34: 115042911097 | B34: 46071.407 | C34: Myharvest Farms | D34: Accelerate Prime | E34: Chennai | F34: Nirmallya Roy Chowdhury | G34: =AVERAGE(S34:T34) -> 4.5 | H34: Very useful | I34: Yes | J34: No | K34: It was just an intro call and was good. | L34: =IF(G34<=3,"Yes","No") -> No | S34: =IF(H34="Extremely useful",5,IF(H34="Very useful",4,IF(H34="Moderately useful",3,IF(H34="Slightly useful",2,IF(H34="Not useful",1))))) -> 4 | T34: =IF(I34="Yes",5,IF(I34="Partly",3,IF(I34="No",1))) -> 5 | U34: =IF(J34="Yes",5,IF(J34="No",1)) -> 1 | V34: =IF(ISBLANK(FeedbackTracker[[#This Row],[Date]]),"",INT(FeedbackTracker[[#This Row],[Date]]-WEEKDAY(FeedbackTracker[[#This Row],[Date]],2)+1)) -> 46069
A35: 115042909248 | B35: 46071.393 | C35: Hogist technologies Pvt Ltd | D35: Accelerate Prime | E35: Chennai | F35: Sriram Chidambaram | G35: =AVERAGE(S35:T35) -> 2.5 | H35: Slightly useful | I35: Partly | J35: No | K35: Was just Ok. | L35: =IF(G35<=3,"Yes","No") -> Yes | N35: Received | O35: Misalignment | P35: Not suggested or connected by us. Was directly connected by HM 11-Mar-2026: Mentor was not aliginging with their problem and they want person from B2B | S35: =IF(H35="Extremely useful",5,IF(H35="Very useful",4,IF(H35="Moderately useful",3,IF(H35="Slightly useful",2,IF(H35="Not useful",1))))) -> 2 | T35: =IF(I35="Yes",5,IF(I35="Partly",3,IF(I35="No",1))) -> 3 | U35: =IF(J35="Yes",5,IF(J35="No",1)) -> 1 | V35: =IF(ISBLANK(FeedbackTracker[[#This Row],[Date]]),"",INT(FeedbackTracker[[#This Row],[Date]]-WEEKDAY(FeedbackTracker[[#This Row],[Date]],2)+1)) -> 46069
A36: 115042335711 | B36: 46070.741 | C36: Atreya Innovations | D36: Accelerate Prime | E36: Pune | F36: Sriram Chadambaram | G36: =AVERAGE(S36:T36) -> 4.5 | H36: Very useful | I36: Yes | J36: No | L36: =IF(G36<=3,"Yes","No") -> No | S36: =IF(H36="Extremely useful",5,IF(H36="Very useful",4,IF(H36="Moderately useful",3,IF(H36="Slightly useful",2,IF(H36="Not useful",1))))) -> 4 | T36: =IF(I36="Yes",5,IF(I36="Partly",3,IF(I36="No",1))) -> 5 | U36: =IF(J36="Yes",5,IF(J36="No",1)) -> 1 | V36: =IF(ISBLANK(FeedbackTracker[[#This Row],[Date]]),"",INT(FeedbackTracker[[#This Row],[Date]]-WEEKDAY(FeedbackTracker[[#This Row],[Date]],2)+1)) -> 46069
A37: 115042305484 | B37: 46070.691 | C37: Gyrodrive | D37: Accelerate Prime | E37: Pune | F37: Garima Mitra | G37: =AVERAGE(S37:T37) -> 4.5 | H37: Very useful | I37: Yes | J37: No | K37: We had a discussion and signed the term sheet and asked to share the term sheet. | L37: =IF(G37<=3,"Yes","No") -> No | S37: =IF(H37="Extremely useful",5,IF(H37="Very useful",4,IF(H37="Moderately useful",3,IF(H37="Slightly useful",2,IF(H37="Not useful",1))))) -> 4 | T37: =IF(I37="Yes",5,IF(I37="Partly",3,IF(I37="No",1))) -> 5 | U37: =IF(J37="Yes",5,IF(J37="No",1)) -> 1 | V37: =IF(ISBLANK(FeedbackTracker[[#This Row],[Date]]),"",INT(FeedbackTracker[[#This Row],[Date]]-WEEKDAY(FeedbackTracker[[#This Row],[Date]],2)+1)) -> 46069
A38: 115042304010 | B38: 46070.686 | C38: Frontierz | D38: Accelerate Prime | E38: Pune | F38: Sandeep Gupta | G38: =AVERAGE(S38:T38) -> 4.5 | H38: Very useful | I38: Yes | J38: No | K38: Overall it was good session and was a guy good. | L38: =IF(G38<=3,"Yes","No") -> No | S38: =IF(H38="Extremely useful",5,IF(H38="Very useful",4,IF(H38="Moderately useful",3,IF(H38="Slightly useful",2,IF(H38="Not useful",1))))) -> 4 | T38: =IF(I38="Yes",5,IF(I38="Partly",3,IF(I38="No",1))) -> 5 | U38: =IF(J38="Yes",5,IF(J38="No",1)) -> 1 | V38: =IF(ISBLANK(FeedbackTracker[[#This Row],[Date]]),"",INT(FeedbackTracker[[#This Row],[Date]]-WEEKDAY(FeedbackTracker[[#This Row],[Date]],2)+1)) -> 46069
A39: 115039714773 | B39: 46065.826 | C39: Leap Info | D39: Accelerate Core | E39: Pune | F39: Sriram Chidambaram | G39: =AVERAGE(S39:T39) -> 5 | H39: Extremely useful | I39: Yes | J39: No | K39: Highly practical and insightful | L39: =IF(G39<=3,"Yes","No") -> No | S39: =IF(H39="Extremely useful",5,IF(H39="Very useful",4,IF(H39="Moderately useful",3,IF(H39="Slightly useful",2,IF(H39="Not useful",1))))) -> 5 | T39: =IF(I39="Yes",5,IF(I39="Partly",3,IF(I39="No",1))) -> 5 | U39: =IF(J39="Yes",5,IF(J39="No",1)) -> 1 | V39: =IF(ISBLANK(FeedbackTracker[[#This Row],[Date]]),"",INT(FeedbackTracker[[#This Row],[Date]]-WEEKDAY(FeedbackTracker[[#This Row],[Date]],2)+1)) -> 46062
A40: 115034932805 | B40: 46058.5 | C40: Manufyx | D40: Accelerate Core | E40: Chennai | F40: Manu kumar | G40: =AVERAGE(S40:T40) -> 4.5 | H40: Very useful | I40: Yes | J40: No | L40: =IF(G40<=3,"Yes","No") -> No | M40: Reached out: Response Received | S40: =IF(H40="Extremely useful",5,IF(H40="Very useful",4,IF(H40="Moderately useful",3,IF(H40="Slightly useful",2,IF(H40="Not useful",1))))) -> 4 | T40: =IF(I40="Yes",5,IF(I40="Partly",3,IF(I40="No",1))) -> 5 | U40: =IF(J40="Yes",5,IF(J40="No",1)) -> 1 | V40: =IF(ISBLANK(FeedbackTracker[[#This Row],[Date]]),"",INT(FeedbackTracker[[#This Row],[Date]]-WEEKDAY(FeedbackTracker[[#This Row],[Date]],2)+1)) -> 46055
A41: 115034142437 | B41: 46057.454 | C41: Foodnest | D41: Accelerate Prime | E41: Pune | F41: Sriram Chidambaram | G41: =AVERAGE(S41:T41) -> 5 | H41: Extremely useful | I41: Yes | J41: Yes | K41: Gave us lot of clarity and roadmap Looking forward for more sessions | L41: =IF(G41<=3,"Yes","No") -> No | S41: =IF(H41="Extremely useful",5,IF(H41="Very useful",4,IF(H41="Moderately useful",3,IF(H41="Slightly useful",2,IF(H41="Not useful",1))))) -> 5 | T41: =IF(I41="Yes",5,IF(I41="Partly",3,IF(I41="No",1))) -> 5 | U41: =IF(J41="Yes",5,IF(J41="No",1)) -> 5 | V41: =IF(ISBLANK(FeedbackTracker[[#This Row],[Date]]),"",INT(FeedbackTracker[[#This Row],[Date]]-WEEKDAY(FeedbackTracker[[#This Row],[Date]],2)+1)) -> 46055
A42: 115033423062 | B42: 46056.495 | C42: Padcare Labs | D42: Accelerate Core | E42: Pune | F42: Mohanakrishnan P | G42: =AVERAGE(S42:T42) -> 4.5 | H42: Very useful | I42: Yes | J42: No | K42: It was a nice discussion with him and got a good insights. | L42: =IF(G42<=3,"Yes","No") -> No | S42: =IF(H42="Extremely useful",5,IF(H42="Very useful",4,IF(H42="Moderately useful",3,IF(H42="Slightly useful",2,IF(H42="Not useful",1))))) -> 4 | T42: =IF(I42="Yes",5,IF(I42="Partly",3,IF(I42="No",1))) -> 5 | U42: =IF(J42="Yes",5,IF(J42="No",1)) -> 1 | V42: =IF(ISBLANK(FeedbackTracker[[#This Row],[Date]]),"",INT(FeedbackTracker[[#This Row],[Date]]-WEEKDAY(FeedbackTracker[[#This Row],[Date]],2)+1)) -> 46055
A43: 115029762864 | B43: 46050.603 | C43: Vaultastic | D43: Accelerate Core | E43: Pune | F43: Anant Sood | G43: =AVERAGE(S43:T43) -> 4.5 | H43: Very useful | I43: Yes | J43: No | K43: Anant has been through the journey of taking his product to the North American Market. His experience can be very valuable in planning out our GTM for this market. | L43: =IF(G43<=3,"Yes","No") -> No | S43: =IF(H43="Extremely useful",5,IF(H43="Very useful",4,IF(H43="Moderately useful",3,IF(H43="Slightly useful",2,IF(H43="Not useful",1))))) -> 4 | T43: =IF(I43="Yes",5,IF(I43="Partly",3,IF(I43="No",1))) -> 5 | U43: =IF(J43="Yes",5,IF(J43="No",1)) -> 1 | V43: =IF(ISBLANK(FeedbackTracker[[#This Row],[Date]]),"",INT(FeedbackTracker[[#This Row],[Date]]-WEEKDAY(FeedbackTracker[[#This Row],[Date]],2)+1)) -> 46048
A44: 115029759318 | B44: 46050.597 | C44: Leap Info | D44: Accelerate Core | E44: Pune | F44: Umesh Uttamchandani | G44: =AVERAGE(S44:T44) -> 4.5 | H44: Very useful | I44: Yes | J44: No | K44: Relatable, To the point and precise. | L44: =IF(G44<=3,"Yes","No") -> No | S44: =IF(H44="Extremely useful",5,IF(H44="Very useful",4,IF(H44="Moderately useful",3,IF(H44="Slightly useful",2,IF(H44="Not useful",1))))) -> 4 | T44: =IF(I44="Yes",5,IF(I44="Partly",3,IF(I44="No",1))) -> 5 | U44: =IF(J44="Yes",5,IF(J44="No",1)) -> 1 | V44: =IF(ISBLANK(FeedbackTracker[[#This Row],[Date]]),"",INT(FeedbackTracker[[#This Row],[Date]]-WEEKDAY(FeedbackTracker[[#This Row],[Date]],2)+1)) -> 46048
A45: 115029736543 | B45: 46050.547 | C45: VideoSDK | D45: Accelerate Core | E45: Ahmedabad | F45: Siddharth Pandey | G45: =AVERAGE(S45:T45) -> 5 | H45: Extremely useful | I45: Yes | J45: No | K45: He is very relatable to the ICP and was forthcoming in offering connects. | L45: =IF(G45<=3,"Yes","No") -> No | S45: =IF(H45="Extremely useful",5,IF(H45="Very useful",4,IF(H45="Moderately useful",3,IF(H45="Slightly useful",2,IF(H45="Not useful",1))))) -> 5 | T45: =IF(I45="Yes",5,IF(I45="Partly",3,IF(I45="No",1))) -> 5 | U45: =IF(J45="Yes",5,IF(J45="No",1)) -> 1 | V45: =IF(ISBLANK(FeedbackTracker[[#This Row],[Date]]),"",INT(FeedbackTracker[[#This Row],[Date]]-WEEKDAY(FeedbackTracker[[#This Row],[Date]],2)+1)) -> 46048
A46: 115029735861 | B46: 46050.54 | C46: Tailor Smart | D46: Accelerate Prime | E46: Pune | F46: Crispino Santamaria | G46: =AVERAGE(S46:T46) -> 4.5 | H46: Very useful | I46: Yes | J46: No | K46: Was a good session | L46: =IF(G46<=3,"Yes","No") -> No | S46: =IF(H46="Extremely useful",5,IF(H46="Very useful",4,IF(H46="Moderately useful",3,IF(H46="Slightly useful",2,IF(H46="Not useful",1))))) -> 4 | T46: =IF(I46="Yes",5,IF(I46="Partly",3,IF(I46="No",1))) -> 5 | U46: =IF(J46="Yes",5,IF(J46="No",1)) -> 1 | V46: =IF(ISBLANK(FeedbackTracker[[#This Row],[Date]]),"",INT(FeedbackTracker[[#This Row],[Date]]-WEEKDAY(FeedbackTracker[[#This Row],[Date]],2)+1)) -> 46048
A47: 115029732350 | B47: 46050.538 | C47: Tailor Smart | D47: Accelerate Prime | E47: Pune | F47: Ashish Mittal | G47: =AVERAGE(S47:T47) -> 4.5 | H47: Very useful | I47: Yes | J47: No | K47: Ashish helped in connecting with corporates | L47: =IF(G47<=3,"Yes","No") -> No | S47: =IF(H47="Extremely useful",5,IF(H47="Very useful",4,IF(H47="Moderately useful",3,IF(H47="Slightly useful",2,IF(H47="Not useful",1))))) -> 4 | T47: =IF(I47="Yes",5,IF(I47="Partly",3,IF(I47="No",1))) -> 5 | U47: =IF(J47="Yes",5,IF(J47="No",1)) -> 1 | V47: =IF(ISBLANK(FeedbackTracker[[#This Row],[Date]]),"",INT(FeedbackTracker[[#This Row],[Date]]-WEEKDAY(FeedbackTracker[[#This Row],[Date]],2)+1)) -> 46048
A48: 115029727801 | B48: 46050.489 | C48: PowerTree | D48: Accelerate Core | E48: Pune Ahmedabad | F48: Satya kiran Gannarapu | G48: =AVERAGE(S48:T48) -> 4.5 | H48: Very useful | I48: Yes | J48: No | K48: Exeperience was good. | L48: =IF(G48<=3,"Yes","No") -> No | S48: =IF(H48="Extremely useful",5,IF(H48="Very useful",4,IF(H48="Moderately useful",3,IF(H48="Slightly useful",2,IF(H48="Not useful",1))))) -> 4 | T48: =IF(I48="Yes",5,IF(I48="Partly",3,IF(I48="No",1))) -> 5 | U48: =IF(J48="Yes",5,IF(J48="No",1)) -> 1 | V48: =IF(ISBLANK(FeedbackTracker[[#This Row],[Date]]),"",INT(FeedbackTracker[[#This Row],[Date]]-WEEKDAY(FeedbackTracker[[#This Row],[Date]],2)+1)) -> 46048
A49: 115029724214 | B49: 46050.519 | C49: Atreya Innovations | D49: Accelerate Prime | E49: Pune | F49: Sriram Chidambaram | G49: =AVERAGE(S49:T49) -> 4.5 | H49: Very useful | I49: Yes | J49: No | K49: I have mentioned yes above. We are working on the steps given by him, and may want to get validated from someone else from the same field. Will be in touch to decide the next steps. Thank you. | L49: =IF(G49<=3,"Yes","No") -> No | M49: Reached out: Response Received | S49: =IF(H49="Extremely useful",5,IF(H49="Very useful",4,IF(H49="Moderately useful",3,IF(H49="Slightly useful",2,IF(H49="Not useful",1))))) -> 4 | T49: =IF(I49="Yes",5,IF(I49="Partly",3,IF(I49="No",1))) -> 5 | U49: =IF(J49="Yes",5,IF(J49="No",1)) -> 1 | V49: =IF(ISBLANK(FeedbackTracker[[#This Row],[Date]]),"",INT(FeedbackTracker[[#This Row],[Date]]-WEEKDAY(FeedbackTracker[[#This Row],[Date]],2)+1)) -> 46048
A50: 115029714292 | B50: 46050.475 | C50: PowerTree | D50: Accelerate Core | E50: Pune Ahmedabad | F50: Nayaz JU Launchpad | G50: =AVERAGE(S50:T50) -> 4.5 | H50: Very useful | I50: Yes | J50: No | K50: The session was insightful and we appreciate the prespective | L50: =IF(G50<=3,"Yes","No") -> No | S50: =IF(H50="Extremely useful",5,IF(H50="Very useful",4,IF(H50="Moderately useful",3,IF(H50="Slightly useful",2,IF(H50="Not useful",1))))) -> 4 | T50: =IF(I50="Yes",5,IF(I50="Partly",3,IF(I50="No",1))) -> 5 | U50: =IF(J50="Yes",5,IF(J50="No",1)) -> 1 | V50: =IF(ISBLANK(FeedbackTracker[[#This Row],[Date]]),"",INT(FeedbackTracker[[#This Row],[Date]]-WEEKDAY(FeedbackTracker[[#This Row],[Date]],2)+1)) -> 46048
A51: 115029714002 | B51: 46050.492 | C51: Nuutjobs | D51: Accelerate Core | E51: Ahmedabad | F51: Gopal Kalra | G51: =AVERAGE(S51:T51) -> 4.5 | H51: Very useful | I51: Yes | J51: No | K51: Need mentor to navigate Digital Marketing | L51: =IF(G51<=3,"Yes","No") -> No | M51: Reached out: Response Received | S51: =IF(H51="Extremely useful",5,IF(H51="Very useful",4,IF(H51="Moderately useful",3,IF(H51="Slightly useful",2,IF(H51="Not useful",1))))) -> 4 | T51: =IF(I51="Yes",5,IF(I51="Partly",3,IF(I51="No",1))) -> 5 | U51: =IF(J51="Yes",5,IF(J51="No",1)) -> 1 | V51: =IF(ISBLANK(FeedbackTracker[[#This Row],[Date]]),"",INT(FeedbackTracker[[#This Row],[Date]]-WEEKDAY(FeedbackTracker[[#This Row],[Date]],2)+1)) -> 46048
A52: 115029706380 | B52: 46050.467 | C52: Dhobi G | D52: Accelerate Prime | E52: Chennai | F52: Krishna Dorai | G52: =AVERAGE(S52:T52) -> 3.5 | H52: Very useful | I52: Partly | J52: Yes | K52: It was a great session. | L52: =IF(G52<=3,"Yes","No") -> No | N52: Received | O52: 1st Intro Call | P52: 17-mar-2026: Marketing guy called and mentioned the session was great and mentor only asked questions and collected the data. Didn't want to connect again as the marketing understood the insights again and is working on them. Will confirm if another session required with him. 17-Mar-2026: Founder told his marketing team head will call us and give proper feedback. He also mentioned that as it was first session, wanted to get connected with him again 13-mar-2026: Not answering the calls 11-mar-2026: Not answering the calls | S52: =IF(H52="Extremely useful",5,IF(H52="Very useful",4,IF(H52="Moderately useful",3,IF(H52="Slightly useful",2,IF(H52="Not useful",1))))) -> 4 | T52: =IF(I52="Yes",5,IF(I52="Partly",3,IF(I52="No",1))) -> 3 | U52: =IF(J52="Yes",5,IF(J52="No",1)) -> 5 | V52: =IF(ISBLANK(FeedbackTracker[[#This Row],[Date]]),"",INT(FeedbackTracker[[#This Row],[Date]]-WEEKDAY(FeedbackTracker[[#This Row],[Date]],2)+1)) -> 46048
A53: 115029703375 | B53: 46050.459 | C53: Gyrodrive | D53: Accelerate Prime | E53: Pune | F53: Sriram Chidambaram | G53: =AVERAGE(S53:T53) -> 5 | H53: Extremely useful | I53: Yes | J53: No | K53: The session was very useful and mentor and HM were helful for us. | L53: =IF(G53<=3,"Yes","No") -> No | S53: =IF(H53="Extremely useful",5,IF(H53="Very useful",4,IF(H53="Moderately useful",3,IF(H53="Slightly useful",2,IF(H53="Not useful",1))))) -> 5 | T53: =IF(I53="Yes",5,IF(I53="Partly",3,IF(I53="No",1))) -> 5 | U53: =IF(J53="Yes",5,IF(J53="No",1)) -> 1 | V53: =IF(ISBLANK(FeedbackTracker[[#This Row],[Date]]),"",INT(FeedbackTracker[[#This Row],[Date]]-WEEKDAY(FeedbackTracker[[#This Row],[Date]],2)+1)) -> 46048
A54: 115025883593 | B54: 46044.747 | C54: Manufyx | D54: Accelerate Core | E54: Chennai | F54: Jayen Kotecha | G54: =AVERAGE(S54:T54) -> 3.5 | H54: Very useful | I54: Partly | J54: No | K54: The mentor was not up to the mark | L54: =IF(G54<=3,"Yes","No") -> No | M54: Reached out: Response Received | N54: Received | O54: Mentor was good but the Founder already was well aware of the topic | P54: 11-mar-2026: The mentor was not able to give new ideas for the session. More mentor connects to be done in marketing. Call was good. Mentor was also good. He himself has good experience in Vendor Quality side hence whatever was shared by Mentor, he was already aware As per him, it was not the Wrong matching either He realized, he need to focus on other area of business. | S54: =IF(H54="Extremely useful",5,IF(H54="Very useful",4,IF(H54="Moderately useful",3,IF(H54="Slightly useful",2,IF(H54="Not useful",1))))) -> 4 | T54: =IF(I54="Yes",5,IF(I54="Partly",3,IF(I54="No",1))) -> 3 | U54: =IF(J54="Yes",5,IF(J54="No",1)) -> 1 | V54: =IF(ISBLANK(FeedbackTracker[[#This Row],[Date]]),"",INT(FeedbackTracker[[#This Row],[Date]]-WEEKDAY(FeedbackTracker[[#This Row],[Date]],2)+1)) -> 46041
A55: 115025880088 | B55: 46044.745 | C55: Exposit Immersive Solution Pvt Ltd | D55: Accelerate Prime | E55: Ahmedabad | F55: Mahesh Natrajan | G55: =AVERAGE(S55:T55) -> 4.5 | H55: Very useful | I55: Yes | J55: No | K55: It was good session and was an experienced mentor. | L55: =IF(G55<=3,"Yes","No") -> No | M55: Reached out: Response Received | S55: =IF(H55="Extremely useful",5,IF(H55="Very useful",4,IF(H55="Moderately useful",3,IF(H55="Slightly useful",2,IF(H55="Not useful",1))))) -> 4 | T55: =IF(I55="Yes",5,IF(I55="Partly",3,IF(I55="No",1))) -> 5 | U55: =IF(J55="Yes",5,IF(J55="No",1)) -> 1 | V55: =IF(ISBLANK(FeedbackTracker[[#This Row],[Date]]),"",INT(FeedbackTracker[[#This Row],[Date]]-WEEKDAY(FeedbackTracker[[#This Row],[Date]],2)+1)) -> 46041
A56: 115025861257 | B56: 46044.716 | C56: Vaultastic | D56: Accelerate Core | E56: Pune | F56: Kumaresh Tirukonda | G56: =AVERAGE(S56:T56) -> 4.5 | H56: Very useful | I56: Yes | J56: Yes | K56: Follow up session with same mentor is required again. | L56: =IF(G56<=3,"Yes","No") -> No | M56: Reached out: Response Received | S56: =IF(H56="Extremely useful",5,IF(H56="Very useful",4,IF(H56="Moderately useful",3,IF(H56="Slightly useful",2,IF(H56="Not useful",1))))) -> 4 | T56: =IF(I56="Yes",5,IF(I56="Partly",3,IF(I56="No",1))) -> 5 | U56: =IF(J56="Yes",5,IF(J56="No",1)) -> 5 | V56: =IF(ISBLANK(FeedbackTracker[[#This Row],[Date]]),"",INT(FeedbackTracker[[#This Row],[Date]]-WEEKDAY(FeedbackTracker[[#This Row],[Date]],2)+1)) -> 46041
A57: 115024940419 | B57: 46043.524 | C57: Stembotix | D57: Accelerate Core | E57: Ahmedabad | F57: Kavya Dehulia | G57: =AVERAGE(S57:T57) -> 3 | H57: Moderately useful | I57: Partly | J57: No | L57: =IF(G57<=3,"Yes","No") -> Yes | M57: Reached out: Response Received | N57: Received | O57: Misalignment | P57: 11-Mar-2026: The mentor was confuesed and was a intro call. Don't need to connect with her. Also she didn't seemed to understand the venture as well. | S57: =IF(H57="Extremely useful",5,IF(H57="Very useful",4,IF(H57="Moderately useful",3,IF(H57="Slightly useful",2,IF(H57="Not useful",1))))) -> 3 | T57: =IF(I57="Yes",5,IF(I57="Partly",3,IF(I57="No",1))) -> 3 | U57: =IF(J57="Yes",5,IF(J57="No",1)) -> 1 | V57: =IF(ISBLANK(FeedbackTracker[[#This Row],[Date]]),"",INT(FeedbackTracker[[#This Row],[Date]]-WEEKDAY(FeedbackTracker[[#This Row],[Date]],2)+1)) -> 46041
A58: 115024937956 | B58: 46043.511 | C58: Raptee Energy Pvt Ltd | D58: Accelerate Core | E58: Chennai | F58: Arnab Chatterjee | G58: =AVERAGE(S58:T58) -> 1 | H58: Not useful | I58: No | J58: No | K58: He didn't spoke anything relevant and mentors is calling multiple times after the call which is not good | L58: =IF(G58<=3,"Yes","No") -> Yes | M58: Reached out: Response Received | N58: Received | O58: Misalignment | P58: 16-mar-2026: Meeting went well. Only Gap there was the type of vehicles he was selling was not what founder is trying to build. He was probably was not fit. He shared that there were some challenges with Arnab, but did not share what challenges. Mentor was kind and nothing wrong. It was just about the Miss alignment. | S58: =IF(H58="Extremely useful",5,IF(H58="Very useful",4,IF(H58="Moderately useful",3,IF(H58="Slightly useful",2,IF(H58="Not useful",1))))) -> 1 | T58: =IF(I58="Yes",5,IF(I58="Partly",3,IF(I58="No",1))) -> 1 | U58: =IF(J58="Yes",5,IF(J58="No",1)) -> 1 | V58: =IF(ISBLANK(FeedbackTracker[[#This Row],[Date]]),"",INT(FeedbackTracker[[#This Row],[Date]]-WEEKDAY(FeedbackTracker[[#This Row],[Date]],2)+1)) -> 46041
A59: 115023428054 | B59: 46041.411 | C59: Raw Pharma | D59: Accelerate Prime | E59: Ahmedabad | F59: Rupaal Singh | G59: =AVERAGE(S59:T59) -> 1.5 | H59: Slightly useful | I59: No | J59: No | K59: Rupal is not fit mentor and was discussing about the topic and was very informal. | L59: =IF(G59<=3,"Yes","No") -> Yes | N59: Received | O59: Misalignment | P59: 11-Mar-2026: Mentor was good but we wern't able to identify next steps as he was from agritech and were are from F&B category | S59: =IF(H59="Extremely useful",5,IF(H59="Very useful",4,IF(H59="Moderately useful",3,IF(H59="Slightly useful",2,IF(H59="Not useful",1))))) -> 2 | T59: =IF(I59="Yes",5,IF(I59="Partly",3,IF(I59="No",1))) -> 1 | U59: =IF(J59="Yes",5,IF(J59="No",1)) -> 1 | V59: =IF(ISBLANK(FeedbackTracker[[#This Row],[Date]]),"",INT(FeedbackTracker[[#This Row],[Date]]-WEEKDAY(FeedbackTracker[[#This Row],[Date]],2)+1)) -> 46041
A60: 115018340690 | B60: 46032.787 | C60: REAGRI - NANOBEE BIOINNOVATIONS | D60: Accelerate Core | E60: Ahmedabad | F60: Pradeep Malu | G60: =AVERAGE(S60:T60) -> 4.5 | H60: Very useful | I60: Yes | J60: No | L60: =IF(G60<=3,"Yes","No") -> No | M60: Reached out: Response Received | S60: =IF(H60="Extremely useful",5,IF(H60="Very useful",4,IF(H60="Moderately useful",3,IF(H60="Slightly useful",2,IF(H60="Not useful",1))))) -> 4 | T60: =IF(I60="Yes",5,IF(I60="Partly",3,IF(I60="No",1))) -> 5 | U60: =IF(J60="Yes",5,IF(J60="No",1)) -> 1 | V60: =IF(ISBLANK(FeedbackTracker[[#This Row],[Date]]),"",INT(FeedbackTracker[[#This Row],[Date]]-WEEKDAY(FeedbackTracker[[#This Row],[Date]],2)+1)) -> 46027
A61: 115017277742 | B61: 46031.017 | C61: Raptee Energy Pvt LTd | D61: Accelerate Core | E61: Chennai | F61: Gokulraj GK | G61: =AVERAGE(S61:T61) -> 5 | H61: Extremely useful | I61: Yes | J61: No | K61: He was perfect. Seemed to understand exactly what I needed. Thanks. | L61: =IF(G61<=3,"Yes","No") -> No | M61: Reached out: Response Received | S61: =IF(H61="Extremely useful",5,IF(H61="Very useful",4,IF(H61="Moderately useful",3,IF(H61="Slightly useful",2,IF(H61="Not useful",1))))) -> 5 | T61: =IF(I61="Yes",5,IF(I61="Partly",3,IF(I61="No",1))) -> 5 | U61: =IF(J61="Yes",5,IF(J61="No",1)) -> 1 | V61: =IF(ISBLANK(FeedbackTracker[[#This Row],[Date]]),"",INT(FeedbackTracker[[#This Row],[Date]]-WEEKDAY(FeedbackTracker[[#This Row],[Date]],2)+1)) -> 46027
A62: 115017009833 | B62: 46030.722 | C62: Jeevtronics | D62: Accelerate Prime | E62: Pune | F62: Dheeresh Manrai | G62: =AVERAGE(S62:T62) -> 5 | H62: Extremely useful | I62: Yes | J62: No | K62: Practical, clear , implementation ready suggestions. Great words of wisdom! | L62: =IF(G62<=3,"Yes","No") -> No | M62: Reached out: Response Received | S62: =IF(H62="Extremely useful",5,IF(H62="Very useful",4,IF(H62="Moderately useful",3,IF(H62="Slightly useful",2,IF(H62="Not useful",1))))) -> 5 | T62: =IF(I62="Yes",5,IF(I62="Partly",3,IF(I62="No",1))) -> 5 | U62: =IF(J62="Yes",5,IF(J62="No",1)) -> 1 | V62: =IF(ISBLANK(FeedbackTracker[[#This Row],[Date]]),"",INT(FeedbackTracker[[#This Row],[Date]]-WEEKDAY(FeedbackTracker[[#This Row],[Date]],2)+1)) -> 46027
A63: 115016261180 | B63: 46029.542 | C63: Stembotix | D63: Accelerate Core | E63: Ahmedabad | F63: Pradeep Rathi | G63: =AVERAGE(S63:T63) -> 3 | H63: Moderately useful | I63: Partly | J63: No | K63: No. | L63: =IF(G63<=3,"Yes","No") -> Yes | M63: No Response: Call Disconnected | N63: Received | O63: Mentor not Satisfied | P63: 11-Mar-2026: The mentor was confused and was a intro call. Don't need to connect with him | S63: =IF(H63="Extremely useful",5,IF(H63="Very useful",4,IF(H63="Moderately useful",3,IF(H63="Slightly useful",2,IF(H63="Not useful",1))))) -> 3 | T63: =IF(I63="Yes",5,IF(I63="Partly",3,IF(I63="No",1))) -> 3 | U63: =IF(J63="Yes",5,IF(J63="No",1)) -> 1 | V63: =IF(ISBLANK(FeedbackTracker[[#This Row],[Date]]),"",INT(FeedbackTracker[[#This Row],[Date]]-WEEKDAY(FeedbackTracker[[#This Row],[Date]],2)+1)) -> 46027
A64: 115015684851 | B64: 46028.762 | C64: Green Pods | D64: Accelerate Prime | E64: Chennai | F64: Arun Sharma | G64: =AVERAGE(S64:T64) -> 2 | H64: Moderately useful | I64: No | J64: No | L64: =IF(G64<=3,"Yes","No") -> Yes | M64: Received | N64: Received | O64: Misalignment | P64: 11-Mar-2026: The suggestion were not reletable and also venture want to connect with new set of metors and convyed this to HM a month ago | S64: =IF(H64="Extremely useful",5,IF(H64="Very useful",4,IF(H64="Moderately useful",3,IF(H64="Slightly useful",2,IF(H64="Not useful",1))))) -> 3 | T64: =IF(I64="Yes",5,IF(I64="Partly",3,IF(I64="No",1))) -> 1 | U64: =IF(J64="Yes",5,IF(J64="No",1)) -> 1 | V64: =IF(ISBLANK(FeedbackTracker[[#This Row],[Date]]),"",INT(FeedbackTracker[[#This Row],[Date]]-WEEKDAY(FeedbackTracker[[#This Row],[Date]],2)+1)) -> 46027
A65: 115015667192 | B65: 46028.729 | C65: REAGRI - NANOBEE BIOINNOVATIONS | D65: Accelerate Core | E65: Ahmedabad | F65: Suhasini Barman | G65: =AVERAGE(S65:T65) -> 4 | H65: Moderately useful | I65: Yes | J65: Yes | K65: As the mentor has deeper understanding of the problem please get us connected again. | L65: =IF(G65<=3,"Yes","No") -> No | N65: No Response: Call Disconnected | P65: 31-Mar-2026: Venture not answering the call. Called thrice. | S65: =IF(H65="Extremely useful",5,IF(H65="Very useful",4,IF(H65="Moderately useful",3,IF(H65="Slightly useful",2,IF(H65="Not useful",1))))) -> 3 | T65: =IF(I65="Yes",5,IF(I65="Partly",3,IF(I65="No",1))) -> 5 | U65: =IF(J65="Yes",5,IF(J65="No",1)) -> 5 | V65: =IF(ISBLANK(FeedbackTracker[[#This Row],[Date]]),"",INT(FeedbackTracker[[#This Row],[Date]]-WEEKDAY(FeedbackTracker[[#This Row],[Date]],2)+1)) -> 46027
A66: 115013186956 | B66: 46022.557 | C66: Alpino | D66: Accelerate Core | E66: Surat | F66: Prashant Mandke | G66: =AVERAGE(S66:T66) -> 3 | H66: Moderately useful | I66: Partly | J66: No | L66: =IF(G66<=3,"Yes","No") -> Yes | M66: Reached out: Response Received | N66: No Response: Call Disconnected | P66: 31-Mar-2026: Called twice but venture isn't answering the calls 21-Mar-2026: Didn't answered the call 17-Mar-2026: Venture will call on saturday 17-mar-2026: Venture not answering the call 13-mar-2026: Venture rejected the call 11-mar-2026: Not answering the calls | S66: =IF(H66="Extremely useful",5,IF(H66="Very useful",4,IF(H66="Moderately useful",3,IF(H66="Slightly useful",2,IF(H66="Not useful",1))))) -> 3 | T66: =IF(I66="Yes",5,IF(I66="Partly",3,IF(I66="No",1))) -> 3 | U66: =IF(J66="Yes",5,IF(J66="No",1)) -> 1 | V66: =IF(ISBLANK(FeedbackTracker[[#This Row],[Date]]),"",INT(FeedbackTracker[[#This Row],[Date]]-WEEKDAY(FeedbackTracker[[#This Row],[Date]],2)+1)) -> 46020
A67: 115012660017 | B67: 46021.482 | C67: Culture x | D67: Accelerate Prime | E67: Ahmedabad | F67: Vignesh Narayanan | G67: =AVERAGE(S67:T67) -> 3.5 | H67: Very useful | I67: Partly | J67: No | L67: =IF(G67<=3,"Yes","No") -> No | N67: Received | O67: 1st Intro Call | P67: 11-Mar-2026: It was an intro call i.e. why, they were not able to identify clear steps. Also HM shared mentor's number with venture and they connected over for further discussion. Connected on 5th Dec g | S67: =IF(H67="Extremely useful",5,IF(H67="Very useful",4,IF(H67="Moderately useful",3,IF(H67="Slightly useful",2,IF(H67="Not useful",1))))) -> 4 | T67: =IF(I67="Yes",5,IF(I67="Partly",3,IF(I67="No",1))) -> 3 | U67: =IF(J67="Yes",5,IF(J67="No",1)) -> 1 | V67: =IF(ISBLANK(FeedbackTracker[[#This Row],[Date]]),"",INT(FeedbackTracker[[#This Row],[Date]]-WEEKDAY(FeedbackTracker[[#This Row],[Date]],2)+1)) -> 46020
A68: 115012289070 | B68: 46020.713 | C68: FTB Organic (Dhombe Patil Foods) | D68: Accelerate Core | E68: Pune | F68: Raj Gulia | G68: =AVERAGE(S68:T68) -> 5 | H68: Extremely useful | I68: Yes | J68: No | K68: Overall good session | L68: =IF(G68<=3,"Yes","No") -> No | S68: =IF(H68="Extremely useful",5,IF(H68="Very useful",4,IF(H68="Moderately useful",3,IF(H68="Slightly useful",2,IF(H68="Not useful",1))))) -> 5 | T68: =IF(I68="Yes",5,IF(I68="Partly",3,IF(I68="No",1))) -> 5 | U68: =IF(J68="Yes",5,IF(J68="No",1)) -> 1 | V68: =IF(ISBLANK(FeedbackTracker[[#This Row],[Date]]),"",INT(FeedbackTracker[[#This Row],[Date]]-WEEKDAY(FeedbackTracker[[#This Row],[Date]],2)+1)) -> 46020
A69: 115012288408 | B69: 46020.731 | C69: Raw Pharma | D69: Accelerate Prime | E69: Ahmedabad | F69: Mukul Bagga | G69: =AVERAGE(S69:T69) -> 3 | H69: Moderately useful | I69: Partly | J69: Yes | K69: Given really good insight about the things. | L69: =IF(G69<=3,"Yes","No") -> Yes | N69: Received | O69: Duplicate | P69: 16-Mar-2026: Mentor discussed quality aspects and was a genius guy, and want to connect with mentor again. He was also very very helpful . Suggested changes founder is implying also. | S69: =IF(H69="Extremely useful",5,IF(H69="Very useful",4,IF(H69="Moderately useful",3,IF(H69="Slightly useful",2,IF(H69="Not useful",1))))) -> 3 | T69: =IF(I69="Yes",5,IF(I69="Partly",3,IF(I69="No",1))) -> 3 | U69: =IF(J69="Yes",5,IF(J69="No",1)) -> 5 | V69: =IF(ISBLANK(FeedbackTracker[[#This Row],[Date]]),"",INT(FeedbackTracker[[#This Row],[Date]]-WEEKDAY(FeedbackTracker[[#This Row],[Date]],2)+1)) -> 46020
A70: 115012177987 | B70: 46020.394 | C70: Dhobi G | D70: Accelerate Prime | E70: Chennai | F70: Manu Kumar | G70: =AVERAGE(S70:T70) -> 5 | H70: Extremely useful | I70: Yes | J70: No | K70: Overall it was good and helpful session and mentor was really helpful. | L70: =IF(G70<=3,"Yes","No") -> No | M70: Duplicate | S70: =IF(H70="Extremely useful",5,IF(H70="Very useful",4,IF(H70="Moderately useful",3,IF(H70="Slightly useful",2,IF(H70="Not useful",1))))) -> 5 | T70: =IF(I70="Yes",5,IF(I70="Partly",3,IF(I70="No",1))) -> 5 | U70: =IF(J70="Yes",5,IF(J70="No",1)) -> 1 | V70: =IF(ISBLANK(FeedbackTracker[[#This Row],[Date]]),"",INT(FeedbackTracker[[#This Row],[Date]]-WEEKDAY(FeedbackTracker[[#This Row],[Date]],2)+1)) -> 46020
A71: 115011737997 | B71: 46018.772 | C71: Univia | D71: Accelerate Core | E71: Ahmedabad | F71: Prashant Mandke | G71: =AVERAGE(S71:T71) -> 5 | H71: Extremely useful | I71: Yes | J71: No | K71: It was a wonderful experience discussing our challenges with him. | L71: =IF(G71<=3,"Yes","No") -> No | M71: Reached out: Response Received | S71: =IF(H71="Extremely useful",5,IF(H71="Very useful",4,IF(H71="Moderately useful",3,IF(H71="Slightly useful",2,IF(H71="Not useful",1))))) -> 5 | T71: =IF(I71="Yes",5,IF(I71="Partly",3,IF(I71="No",1))) -> 5 | U71: =IF(J71="Yes",5,IF(J71="No",1)) -> 1 | V71: =IF(ISBLANK(FeedbackTracker[[#This Row],[Date]]),"",INT(FeedbackTracker[[#This Row],[Date]]-WEEKDAY(FeedbackTracker[[#This Row],[Date]],2)+1)) -> 46013
A72: 115010691070 | B72: 46015.404 | C72: Univia | D72: Accelerate Core | E72: Ahmedabad | F72: Prashant Mandke | G72: =AVERAGE(S72:T72) -> 4.5 | H72: Very useful | I72: Yes | J72: No | K72: The session was very helpful for our execution part. | L72: =IF(G72<=3,"Yes","No") -> No | N72: Duplicate | O72: Duplicate | P72: Duplicate | S72: =IF(H72="Extremely useful",5,IF(H72="Very useful",4,IF(H72="Moderately useful",3,IF(H72="Slightly useful",2,IF(H72="Not useful",1))))) -> 4 | T72: =IF(I72="Yes",5,IF(I72="Partly",3,IF(I72="No",1))) -> 5 | U72: =IF(J72="Yes",5,IF(J72="No",1)) -> 1 | V72: =IF(ISBLANK(FeedbackTracker[[#This Row],[Date]]),"",INT(FeedbackTracker[[#This Row],[Date]]-WEEKDAY(FeedbackTracker[[#This Row],[Date]],2)+1)) -> 46013
A73: 115010658032 | B73: 46015.406 | C73: VideoSDK | D73: Accelerate Core | E73: Ahmedabad | F73: Siddharth Pandey | G73: =AVERAGE(S73:T73) -> 5 | H73: Extremely useful | I73: Yes | J73: No | K73: Very relevant persona | L73: =IF(G73<=3,"Yes","No") -> No | M73: Reached out: Response Received | N73: Duplicate | O73: Duplicate | P73: Duplicate | S73: =IF(H73="Extremely useful",5,IF(H73="Very useful",4,IF(H73="Moderately useful",3,IF(H73="Slightly useful",2,IF(H73="Not useful",1))))) -> 5 | T73: =IF(I73="Yes",5,IF(I73="Partly",3,IF(I73="No",1))) -> 5 | U73: =IF(J73="Yes",5,IF(J73="No",1)) -> 1 | V73: =IF(ISBLANK(FeedbackTracker[[#This Row],[Date]]),"",INT(FeedbackTracker[[#This Row],[Date]]-WEEKDAY(FeedbackTracker[[#This Row],[Date]],2)+1)) -> 46013
A74: 115010656706 | B74: 46015.402 | C74: Manufyx | D74: Accelerate Core | E74: Chennai | F74: Sanjay Sharma | G74: =AVERAGE(S74:T74) -> 4 | H74: Moderately useful | I74: Yes | J74: No | K74: The session was very nice and Wadhwani is giving us what we need. | L74: =IF(G74<=3,"Yes","No") -> No | N74: Received | O74: Duplicate | P74: 11-MAR-2026: The venture mentioned moderately useful was mentioned by mistake | S74: =IF(H74="Extremely useful",5,IF(H74="Very useful",4,IF(H74="Moderately useful",3,IF(H74="Slightly useful",2,IF(H74="Not useful",1))))) -> 3 | T74: =IF(I74="Yes",5,IF(I74="Partly",3,IF(I74="No",1))) -> 5 | U74: =IF(J74="Yes",5,IF(J74="No",1)) -> 1 | V74: =IF(ISBLANK(FeedbackTracker[[#This Row],[Date]]),"",INT(FeedbackTracker[[#This Row],[Date]]-WEEKDAY(FeedbackTracker[[#This Row],[Date]],2)+1)) -> 46013
A75: 115010120828 | B75: 46014.411 | C75: Redicine Medsol | D75: Accelerate Prime | E75: Ahmedabad | F75: Vaibhav Tewari | G75: =AVERAGE(S75:T75) -> 5 | H75: Extremely useful | I75: Yes | J75: No | L75: =IF(G75<=3,"Yes","No") -> No | S75: =IF(H75="Extremely useful",5,IF(H75="Very useful",4,IF(H75="Moderately useful",3,IF(H75="Slightly useful",2,IF(H75="Not useful",1))))) -> 5 | T75: =IF(I75="Yes",5,IF(I75="Partly",3,IF(I75="No",1))) -> 5 | U75: =IF(J75="Yes",5,IF(J75="No",1)) -> 1 | V75: =IF(ISBLANK(FeedbackTracker[[#This Row],[Date]]),"",INT(FeedbackTracker[[#This Row],[Date]]-WEEKDAY(FeedbackTracker[[#This Row],[Date]],2)+1)) -> 46013
A76: 115010117943 | B76: 46014.384 | C76: Tailor Smart | D76: Accelerate Prime | E76: Pune | F76: Anant Sood | G76: =AVERAGE(S76:T76) -> 3 | H76: Moderately useful | I76: Partly | J76: Yes | K76: The session was good and had vast experience. But was not aligned with our goals. | L76: =IF(G76<=3,"Yes","No") -> Yes | M76: Reached out: Response Received | N76: Received | O76: Misalignment | P76: 16-mar-2026: Venture are looking someone more specific in B2B and venture like them who making revenue like us not who are at initial. Also venture raised a request to get connect with Kedar for more asks. | S76: =IF(H76="Extremely useful",5,IF(H76="Very useful",4,IF(H76="Moderately useful",3,IF(H76="Slightly useful",2,IF(H76="Not useful",1))))) -> 3 | T76: =IF(I76="Yes",5,IF(I76="Partly",3,IF(I76="No",1))) -> 3 | U76: =IF(J76="Yes",5,IF(J76="No",1)) -> 5 | V76: =IF(ISBLANK(FeedbackTracker[[#This Row],[Date]]),"",INT(FeedbackTracker[[#This Row],[Date]]-WEEKDAY(FeedbackTracker[[#This Row],[Date]],2)+1)) -> 46013
A77: 115010117925 | B77: 46014.396 | C77: Tailor Smart | D77: Accelerate Prime | E77: Pune | F77: Kumaresh Tirukonda | G77: =AVERAGE(S77:T77) -> 3 | H77: Moderately useful | I77: Partly | J77: Yes | K77: The session was good and had vast experience and another session will same mentor will be required. | L77: =IF(G77<=3,"Yes","No") -> Yes | M77: No Response: Call Disconnected | N77: Received | O77: 1st Intro Call | P77: 16-Mar-2026: The session was good and had vast experience and another session will same mentor will be required. | S77: =IF(H77="Extremely useful",5,IF(H77="Very useful",4,IF(H77="Moderately useful",3,IF(H77="Slightly useful",2,IF(H77="Not useful",1))))) -> 3 | T77: =IF(I77="Yes",5,IF(I77="Partly",3,IF(I77="No",1))) -> 3 | U77: =IF(J77="Yes",5,IF(J77="No",1)) -> 5 | V77: =IF(ISBLANK(FeedbackTracker[[#This Row],[Date]]),"",INT(FeedbackTracker[[#This Row],[Date]]-WEEKDAY(FeedbackTracker[[#This Row],[Date]],2)+1)) -> 46013
A78: 115009560473 | B78: 46013.407 | C78: Mangopoint | D78: Accelerate Core | E78: Chennai | F78: Raj Gulia | G78: =AVERAGE(S78:T78) -> 5 | H78: Extremely useful | I78: Yes | J78: No | L78: =IF(G78<=3,"Yes","No") -> No | S78: =IF(H78="Extremely useful",5,IF(H78="Very useful",4,IF(H78="Moderately useful",3,IF(H78="Slightly useful",2,IF(H78="Not useful",1))))) -> 5 | T78: =IF(I78="Yes",5,IF(I78="Partly",3,IF(I78="No",1))) -> 5 | U78: =IF(J78="Yes",5,IF(J78="No",1)) -> 1 | V78: =IF(ISBLANK(FeedbackTracker[[#This Row],[Date]]),"",INT(FeedbackTracker[[#This Row],[Date]]-WEEKDAY(FeedbackTracker[[#This Row],[Date]],2)+1)) -> 46013
A79: 115008303612 | B79: 46010.467 | C79: Aeronero Solutions Private Limited | D79: Accelerate Core | E79: Chennai | F79: B Gopalakrishnan | G79: =AVERAGE(S79:T79) -> 3.5 | H79: Very useful | I79: Partly | J79: Yes | K79: Very knowledegable | L79: =IF(G79<=3,"Yes","No") -> No | N79: Received | O79: 1st Intro Call | P79: 13-Mar-2026: IT WAS FIRST INTRO ROUND AND THAT IS WHY MENTIONED PARTLY AND WANT TO CONNECT WITH MENTOR AGAIN | S79: =IF(H79="Extremely useful",5,IF(H79="Very useful",4,IF(H79="Moderately useful",3,IF(H79="Slightly useful",2,IF(H79="Not useful",1))))) -> 4 | T79: =IF(I79="Yes",5,IF(I79="Partly",3,IF(I79="No",1))) -> 3 | U79: =IF(J79="Yes",5,IF(J79="No",1)) -> 5 | V79: =IF(ISBLANK(FeedbackTracker[[#This Row],[Date]]),"",INT(FeedbackTracker[[#This Row],[Date]]-WEEKDAY(FeedbackTracker[[#This Row],[Date]],2)+1)) -> 46006
A80: 115008276429 | B80: 46010.397 | C80: LeanKloud | D80: Accelerate Prime | E80: Chennai | F80: Ashish Mittal | G80: =AVERAGE(S80:T80) -> 3.5 | H80: Very useful | I80: Partly | J80: Yes | K80: We could not complete the call as we ran out of time. Ashish understands this space well and we have agreed to speak again shortly | L80: =IF(G80<=3,"Yes","No") -> No | M80: Duplicate | N80: No Response: Call Disconnected | P80: 31-Mar-2026: Called twice but venture is not answering the calls again 17-Mar-2026: venture not replying, but as per the remarks mentioned in the feedback, the session was good. 16-mar-2026: Venture not replying | S80: =IF(H80="Extremely useful",5,IF(H80="Very useful",4,IF(H80="Moderately useful",3,IF(H80="Slightly useful",2,IF(H80="Not useful",1))))) -> 4 | T80: =IF(I80="Yes",5,IF(I80="Partly",3,IF(I80="No",1))) -> 3 | U80: =IF(J80="Yes",5,IF(J80="No",1)) -> 5 | V80: =IF(ISBLANK(FeedbackTracker[[#This Row],[Date]]),"",INT(FeedbackTracker[[#This Row],[Date]]-WEEKDAY(FeedbackTracker[[#This Row],[Date]],2)+1)) -> 46006
A81: 115007761748 | B81: 46009.813 | C81: Eventbeep | D81: Accelerate Prime | E81: Pune | F81: Ashish Mittal | G81: =AVERAGE(S81:T81) -> 5 | H81: Extremely useful | I81: Yes | J81: No | K81: Sessions were very helpful and informative plus the mentor has been really helpful in referring us to more clients | L81: =IF(G81<=3,"Yes","No") -> No | M81: Reached out: Response Received | S81: =IF(H81="Extremely useful",5,IF(H81="Very useful",4,IF(H81="Moderately useful",3,IF(H81="Slightly useful",2,IF(H81="Not useful",1))))) -> 5 | T81: =IF(I81="Yes",5,IF(I81="Partly",3,IF(I81="No",1))) -> 5 | U81: =IF(J81="Yes",5,IF(J81="No",1)) -> 1 | V81: =IF(ISBLANK(FeedbackTracker[[#This Row],[Date]]),"",INT(FeedbackTracker[[#This Row],[Date]]-WEEKDAY(FeedbackTracker[[#This Row],[Date]],2)+1)) -> 46006
A82: 115007336842 | B82: 46009.387 | C82: NG Earsafe | D82: Accelerate Core | E82: Ahmedabad | F82: Prem Sanjay Vuthandam | G82: =AVERAGE(S82:T82) -> 4.5 | H82: Very useful | I82: Yes | J82: No | K82: The session was good and decent. | L82: =IF(G82<=3,"Yes","No") -> No | M82: Reached out: Response Received | S82: =IF(H82="Extremely useful",5,IF(H82="Very useful",4,IF(H82="Moderately useful",3,IF(H82="Slightly useful",2,IF(H82="Not useful",1))))) -> 4 | T82: =IF(I82="Yes",5,IF(I82="Partly",3,IF(I82="No",1))) -> 5 | U82: =IF(J82="Yes",5,IF(J82="No",1)) -> 1 | V82: =IF(ISBLANK(FeedbackTracker[[#This Row],[Date]]),"",INT(FeedbackTracker[[#This Row],[Date]]-WEEKDAY(FeedbackTracker[[#This Row],[Date]],2)+1)) -> 46006
A83: 115007336371 | B83: 46009.406 | C83: Prime UAV | D83: Accelerate Prime | E83: Ahmedabad | F83: Sriram Chidambaram | G83: =AVERAGE(S83:T83) -> 3.5 | H83: Very useful | I83: Partly | J83: No | K83: He was given good vision and steps for develope a new team of our organisation. Thanks for support and guidance. | L83: =IF(G83<=3,"Yes","No") -> No | N83: Duplicate | O83: Duplicate | P83: Duplicate | S83: =IF(H83="Extremely useful",5,IF(H83="Very useful",4,IF(H83="Moderately useful",3,IF(H83="Slightly useful",2,IF(H83="Not useful",1))))) -> 4 | T83: =IF(I83="Yes",5,IF(I83="Partly",3,IF(I83="No",1))) -> 3 | U83: =IF(J83="Yes",5,IF(J83="No",1)) -> 1 | V83: =IF(ISBLANK(FeedbackTracker[[#This Row],[Date]]),"",INT(FeedbackTracker[[#This Row],[Date]]-WEEKDAY(FeedbackTracker[[#This Row],[Date]],2)+1)) -> 46006
A84: 115007335452 | B84: 46009.403 | C84: Prime UAV | D84: Accelerate Prime | E84: Ahmedabad | F84: Sriram Chidambaram | G84: =AVERAGE(S84:T84) -> 3.5 | H84: Very useful | I84: Partly | J84: No | K84: They given some good vision for business development steps and that is helpful for our | L84: =IF(G84<=3,"Yes","No") -> No | N84: Received | O84: 1st Intro Call | P84: 16-Mar-2026: The sessiion was an introductory one that's why it is Partly. Want to connect with some other mentor and conveyed it to HM. | S84: =IF(H84="Extremely useful",5,IF(H84="Very useful",4,IF(H84="Moderately useful",3,IF(H84="Slightly useful",2,IF(H84="Not useful",1))))) -> 4 | T84: =IF(I84="Yes",5,IF(I84="Partly",3,IF(I84="No",1))) -> 3 | U84: =IF(J84="Yes",5,IF(J84="No",1)) -> 1 | V84: =IF(ISBLANK(FeedbackTracker[[#This Row],[Date]]),"",INT(FeedbackTracker[[#This Row],[Date]]-WEEKDAY(FeedbackTracker[[#This Row],[Date]],2)+1)) -> 46006
A85: 115007047056 | B85: 46009.009 | C85: JidokaTechnologies | D85: Accelerate Core | E85: Chennai | F85: Ramkumar Subramanian | G85: =AVERAGE(S85:T85) -> 3 | H85: Moderately useful | I85: Partly | J85: Yes | K85: We have sent a set of follow up for connections in USA as the ask/action item. Awaiting feedback. | L85: =IF(G85<=3,"Yes","No") -> Yes | M85: Reached out: Response Received | N85: Received | O85: Misalignment | P85: 31-Mar-2026: Mentor wasn't upto their expectation. Venture conveyed this to HM and still not a reply from HM. 17-Mar-2026: venture not answering 16-mar-2026: Venture Rejected my call | S85: =IF(H85="Extremely useful",5,IF(H85="Very useful",4,IF(H85="Moderately useful",3,IF(H85="Slightly useful",2,IF(H85="Not useful",1))))) -> 3 | T85: =IF(I85="Yes",5,IF(I85="Partly",3,IF(I85="No",1))) -> 3 | U85: =IF(J85="Yes",5,IF(J85="No",1)) -> 5 | V85: =IF(ISBLANK(FeedbackTracker[[#This Row],[Date]]),"",INT(FeedbackTracker[[#This Row],[Date]]-WEEKDAY(FeedbackTracker[[#This Row],[Date]],2)+1)) -> 46006
A86: 115006771773 | B86: 46008.724 | C86: Vaultastic | D86: Accelerate Core | E86: Pune | F86: Sriram Chidambaram | G86: =AVERAGE(S86:T86) -> 4.5 | H86: Very useful | I86: Yes | J86: No | K86: Gained very useful feedback in helping us simplify and sharpen our pitch deck and positioning of our company for investors. | L86: =IF(G86<=3,"Yes","No") -> No | M86: Pending Reply | S86: =IF(H86="Extremely useful",5,IF(H86="Very useful",4,IF(H86="Moderately useful",3,IF(H86="Slightly useful",2,IF(H86="Not useful",1))))) -> 4 | T86: =IF(I86="Yes",5,IF(I86="Partly",3,IF(I86="No",1))) -> 5 | U86: =IF(J86="Yes",5,IF(J86="No",1)) -> 1 | V86: =IF(ISBLANK(FeedbackTracker[[#This Row],[Date]]),"",INT(FeedbackTracker[[#This Row],[Date]]-WEEKDAY(FeedbackTracker[[#This Row],[Date]],2)+1)) -> 46006
A87: 115006769848 | B87: 46008.718 | C87: Vaultastic | D87: Accelerate Core | E87: Pune | F87: Ashish Mittal | G87: =AVERAGE(S87:T87) -> 4.5 | H87: Very useful | I87: Yes | J87: No | K87: Gained very useful perspectives in validating our GTM plans. | L87: =IF(G87<=3,"Yes","No") -> No | M87: Reached out: Response Received | S87: =IF(H87="Extremely useful",5,IF(H87="Very useful",4,IF(H87="Moderately useful",3,IF(H87="Slightly useful",2,IF(H87="Not useful",1))))) -> 4 | T87: =IF(I87="Yes",5,IF(I87="Partly",3,IF(I87="No",1))) -> 5 | U87: =IF(J87="Yes",5,IF(J87="No",1)) -> 1 | V87: =IF(ISBLANK(FeedbackTracker[[#This Row],[Date]]),"",INT(FeedbackTracker[[#This Row],[Date]]-WEEKDAY(FeedbackTracker[[#This Row],[Date]],2)+1)) -> 46006
A88: 115006767952 | B88: 46008.718 | C88: amPICQ | D88: Accelerate Prime | E88: Pune | F88: Mohit Monga | G88: =AVERAGE(S88:T88) -> 1.5 | H88: Slightly useful | I88: No | J88: Yes | K88: It was unclear as to what the mentor wanted in the end. He mentioned he would want to formalize the discussion the next time we had it. He was maybe suggesting that he would want to become a consultant of the company via a formal contract to interact again. | L88: =IF(G88<=3,"Yes","No") -> Yes | M88: Duplicate | N88: Received | O88: Misalignment | P88: 17-Mar-2026: Mentor was not aligned with venture's technology 16-Mar-2026: Venture didn't received my call | S88: =IF(H88="Extremely useful",5,IF(H88="Very useful",4,IF(H88="Moderately useful",3,IF(H88="Slightly useful",2,IF(H88="Not useful",1))))) -> 2 | T88: =IF(I88="Yes",5,IF(I88="Partly",3,IF(I88="No",1))) -> 1 | U88: =IF(J88="Yes",5,IF(J88="No",1)) -> 5 | V88: =IF(ISBLANK(FeedbackTracker[[#This Row],[Date]]),"",INT(FeedbackTracker[[#This Row],[Date]]-WEEKDAY(FeedbackTracker[[#This Row],[Date]],2)+1)) -> 46006
A89: 115006766979 | B89: 46008.718 | C89: amPICQ | D89: Accelerate Prime | E89: Pune | F89: Amiya Srivastava | G89: =AVERAGE(S89:T89) -> 4 | H89: Moderately useful | I89: Yes | J89: No | L89: =IF(G89<=3,"Yes","No") -> No | M89: Reached out: Response Received | N89: Pending Reply | P89: 1-April-2026: Asked to call after sometime | S89: =IF(H89="Extremely useful",5,IF(H89="Very useful",4,IF(H89="Moderately useful",3,IF(H89="Slightly useful",2,IF(H89="Not useful",1))))) -> 3 | T89: =IF(I89="Yes",5,IF(I89="Partly",3,IF(I89="No",1))) -> 5 | U89: =IF(J89="Yes",5,IF(J89="No",1)) -> 1 | V89: =IF(ISBLANK(FeedbackTracker[[#This Row],[Date]]),"",INT(FeedbackTracker[[#This Row],[Date]]-WEEKDAY(FeedbackTracker[[#This Row],[Date]],2)+1)) -> 46006
A90: 115006764647 | B90: 46008.708 | C90: Stem Tech | D90: Accelerate Prime | E90: Pune | F90: Dheeresh Manrai | G90: =AVERAGE(S90:T90) -> 3 | H90: Moderately useful | I90: Partly | J90: Yes | K90: He seemed knowledgable and had domain expertise in sales. I enjoyed the interaction and learning about his background and journey in medical device space. However, I did not get actionable insights for - 1. south asia market expansion and launching innovative medical device in these countries. | L90: =IF(G90<=3,"Yes","No") -> Yes | N90: Received | O90: Misalignment | P90: 16-Mar-2026: He has delt with infra related prodcuts and venture has products with someting different and they want someone more relatable to our feild i.e in consumables devices | S90: =IF(H90="Extremely useful",5,IF(H90="Very useful",4,IF(H90="Moderately useful",3,IF(H90="Slightly useful",2,IF(H90="Not useful",1))))) -> 3 | T90: =IF(I90="Yes",5,IF(I90="Partly",3,IF(I90="No",1))) -> 3 | U90: =IF(J90="Yes",5,IF(J90="No",1)) -> 5 | V90: =IF(ISBLANK(FeedbackTracker[[#This Row],[Date]]),"",INT(FeedbackTracker[[#This Row],[Date]]-WEEKDAY(FeedbackTracker[[#This Row],[Date]],2)+1)) -> 46006
A91: 115006760019 | B91: 46008.705 | C91: Startoon Labs | D91: Accelerate Prime | E91: Hyderabad | F91: Dheeraj | G91: =AVERAGE(S91:T91) -> 1.5 | H91: Slightly useful | I91: No | J91: No | K91: I have out my asks out to Washwani, but have not yet received much help, though I am in touch with the wadhwani team and awaiting for the support. | L91: =IF(G91<=3,"Yes","No") -> Yes | O91: Duplicate | P91: Duplicate | S91: =IF(H91="Extremely useful",5,IF(H91="Very useful",4,IF(H91="Moderately useful",3,IF(H91="Slightly useful",2,IF(H91="Not useful",1))))) -> 2 | T91: =IF(I91="Yes",5,IF(I91="Partly",3,IF(I91="No",1))) -> 1 | U91: =IF(J91="Yes",5,IF(J91="No",1)) -> 1 | V91: =IF(ISBLANK(FeedbackTracker[[#This Row],[Date]]),"",INT(FeedbackTracker[[#This Row],[Date]]-WEEKDAY(FeedbackTracker[[#This Row],[Date]],2)+1)) -> 46006
A92: 115006758570 | B92: 46008.665 | C92: Startoon Labs | D92: Accelerate Prime | E92: Hyderabad | F92: Dheeresh Manrai | G92: =AVERAGE(S92:T92) -> 2 | H92: Moderately useful | I92: No | J92: No | K92: Not upto the mark. I have out my asks out to Washwani, but have not yet received much help, though I am in touch with the wadhwani team and awaiting for the support. | L92: =IF(G92<=3,"Yes","No") -> Yes | N92: Received | O92: Misalignment | P92: 17-Mar-2026: The venture prefers a mentor connection focused more on enabling relevant business connections rather than just general guidance. They are looking for introductions through the Wadhwani network (e.g., hospitals or healthcare chains) that can directly support business opportunities. As highlighted in feedback and calls, the current HM support has been limited, and the venture is seeking stronger, more relevant connects where we can add value. 16-mar-2026: Venture rejected the call | S92: =IF(H92="Extremely useful",5,IF(H92="Very useful",4,IF(H92="Moderately useful",3,IF(H92="Slightly useful",2,IF(H92="Not useful",1))))) -> 3 | T92: =IF(I92="Yes",5,IF(I92="Partly",3,IF(I92="No",1))) -> 1 | U92: =IF(J92="Yes",5,IF(J92="No",1)) -> 1 | V92: =IF(ISBLANK(FeedbackTracker[[#This Row],[Date]]),"",INT(FeedbackTracker[[#This Row],[Date]]-WEEKDAY(FeedbackTracker[[#This Row],[Date]],2)+1)) -> 46006
A93: 115006731217 | B93: 46008.655 | C93: VideoSDK | D93: Accelerate Core | E93: Ahmedabad | F93: Dr. Sudin Baraokar | G93: =AVERAGE(S93:T93) -> 4.5 | H93: Very useful | I93: Yes | J93: No | K93: He was factual and accurate for us. | L93: =IF(G93<=3,"Yes","No") -> No | S93: =IF(H93="Extremely useful",5,IF(H93="Very useful",4,IF(H93="Moderately useful",3,IF(H93="Slightly useful",2,IF(H93="Not useful",1))))) -> 4 | T93: =IF(I93="Yes",5,IF(I93="Partly",3,IF(I93="No",1))) -> 5 | U93: =IF(J93="Yes",5,IF(J93="No",1)) -> 1 | V93: =IF(ISBLANK(FeedbackTracker[[#This Row],[Date]]),"",INT(FeedbackTracker[[#This Row],[Date]]-WEEKDAY(FeedbackTracker[[#This Row],[Date]],2)+1)) -> 46006
A94: 115006727644 | B94: 46008.652 | C94: PowerTree | D94: Accelerate Core | E94: Pune Ahmedabad | F94: Sriram Chidambaram | G94: =AVERAGE(S94:T94) -> 4.5 | H94: Very useful | I94: Yes | J94: No | K94: The session was good and clear | L94: =IF(G94<=3,"Yes","No") -> No | S94: =IF(H94="Extremely useful",5,IF(H94="Very useful",4,IF(H94="Moderately useful",3,IF(H94="Slightly useful",2,IF(H94="Not useful",1))))) -> 4 | T94: =IF(I94="Yes",5,IF(I94="Partly",3,IF(I94="No",1))) -> 5 | U94: =IF(J94="Yes",5,IF(J94="No",1)) -> 1 | V94: =IF(ISBLANK(FeedbackTracker[[#This Row],[Date]]),"",INT(FeedbackTracker[[#This Row],[Date]]-WEEKDAY(FeedbackTracker[[#This Row],[Date]],2)+1)) -> 46006
A95: 115006724700 | B95: 46008.648 | C95: Urdhvam | D95: Accelerate Core | E95: Pune | F95: Krishna Dorai | G95: =AVERAGE(S95:T95) -> 4.5 | H95: Very useful | I95: Yes | J95: No | K95: Mentor was perfect. | L95: =IF(G95<=3,"Yes","No") -> No | M95: Reached out: Response Received | S95: =IF(H95="Extremely useful",5,IF(H95="Very useful",4,IF(H95="Moderately useful",3,IF(H95="Slightly useful",2,IF(H95="Not useful",1))))) -> 4 | T95: =IF(I95="Yes",5,IF(I95="Partly",3,IF(I95="No",1))) -> 5 | U95: =IF(J95="Yes",5,IF(J95="No",1)) -> 1 | V95: =IF(ISBLANK(FeedbackTracker[[#This Row],[Date]]),"",INT(FeedbackTracker[[#This Row],[Date]]-WEEKDAY(FeedbackTracker[[#This Row],[Date]],2)+1)) -> 46006
A96: 115006697342 | B96: 46008.603 | C96: Nuutjobs | D96: Accelerate Core | E96: Ahmedabad | F96: Gopal Kalra | G96: =AVERAGE(S96:T96) -> 4.5 | H96: Very useful | I96: Yes | J96: No | K96: Mentor told there is a workshop for Finannce and want to know more | L96: =IF(G96<=3,"Yes","No") -> No | S96: =IF(H96="Extremely useful",5,IF(H96="Very useful",4,IF(H96="Moderately useful",3,IF(H96="Slightly useful",2,IF(H96="Not useful",1))))) -> 4 | T96: =IF(I96="Yes",5,IF(I96="Partly",3,IF(I96="No",1))) -> 5 | U96: =IF(J96="Yes",5,IF(J96="No",1)) -> 1 | V96: =IF(ISBLANK(FeedbackTracker[[#This Row],[Date]]),"",INT(FeedbackTracker[[#This Row],[Date]]-WEEKDAY(FeedbackTracker[[#This Row],[Date]],2)+1)) -> 46006
A97: 115006696828 | B97: 46008.606 | C97: Nuutjobs | D97: Accelerate Core | E97: Ahmedabad | F97: Vignesh Narayanan | G97: =AVERAGE(S97:T97) -> 4.5 | H97: Very useful | I97: Yes | J97: No | K97: Mentor told there is a workshop for Finannce and want to know more | L97: =IF(G97<=3,"Yes","No") -> No | S97: =IF(H97="Extremely useful",5,IF(H97="Very useful",4,IF(H97="Moderately useful",3,IF(H97="Slightly useful",2,IF(H97="Not useful",1))))) -> 4 | T97: =IF(I97="Yes",5,IF(I97="Partly",3,IF(I97="No",1))) -> 5 | U97: =IF(J97="Yes",5,IF(J97="No",1)) -> 1 | V97: =IF(ISBLANK(FeedbackTracker[[#This Row],[Date]]),"",INT(FeedbackTracker[[#This Row],[Date]]-WEEKDAY(FeedbackTracker[[#This Row],[Date]],2)+1)) -> 46006
A98: 115006665803 | B98: 46008.557 | C98: Atreya Innovations | D98: Accelerate Prime | E98: Pune | F98: Crispino Santamaria | G98: =AVERAGE(S98:T98) -> 3 | H98: Moderately useful | I98: Partly | J98: Yes | L98: =IF(G98<=3,"Yes","No") -> Yes | N98: Received | O98: Mentor was good but the Founder already was well aware of the topic | P98: 17-mar-2026: The session was good and the mentor shared useful insights. However, most of the points discussed are things the team is already working on, so there wasn’t anything significantly new. They said, they are implementing the suggestions shared and found the mentor helpful. If needed, they would like to reconnect with the mentor in the future. 13-Mar-2026: Called twice but mentor not answering | S98: =IF(H98="Extremely useful",5,IF(H98="Very useful",4,IF(H98="Moderately useful",3,IF(H98="Slightly useful",2,IF(H98="Not useful",1))))) -> 3 | T98: =IF(I98="Yes",5,IF(I98="Partly",3,IF(I98="No",1))) -> 3 | U98: =IF(J98="Yes",5,IF(J98="No",1)) -> 5 | V98: =IF(ISBLANK(FeedbackTracker[[#This Row],[Date]]),"",INT(FeedbackTracker[[#This Row],[Date]]-WEEKDAY(FeedbackTracker[[#This Row],[Date]],2)+1)) -> 46006
A99: 115006614055 | B99: 46008.451 | C99: Jeevtronics | D99: Accelerate Prime | E99: Pune | F99: Crispino Santamaria | G99: =AVERAGE(S99:T99) -> 4.5 | H99: Very useful | I99: Yes | J99: No | K99: Good start at least. | L99: =IF(G99<=3,"Yes","No") -> No | S99: =IF(H99="Extremely useful",5,IF(H99="Very useful",4,IF(H99="Moderately useful",3,IF(H99="Slightly useful",2,IF(H99="Not useful",1))))) -> 4 | T99: =IF(I99="Yes",5,IF(I99="Partly",3,IF(I99="No",1))) -> 5 | U99: =IF(J99="Yes",5,IF(J99="No",1)) -> 1 | V99: =IF(ISBLANK(FeedbackTracker[[#This Row],[Date]]),"",INT(FeedbackTracker[[#This Row],[Date]]-WEEKDAY(FeedbackTracker[[#This Row],[Date]],2)+1)) -> 46006
A100: 115006165834 | B100: 46007.905 | C100: Indian Drivers | D100: Accelerate Core | E100: Pune | F100: Crispino Santamaria | G100: =AVERAGE(S100:T100) -> 4.5 | H100: Very useful | I100: Yes | J100: No | K100: Overall good suggestions shared | L100: =IF(G100<=3,"Yes","No") -> No | M100: Reached out: Response Received | S100: =IF(H100="Extremely useful",5,IF(H100="Very useful",4,IF(H100="Moderately useful",3,IF(H100="Slightly useful",2,IF(H100="Not useful",1))))) -> 4 | T100: =IF(I100="Yes",5,IF(I100="Partly",3,IF(I100="No",1))) -> 5 | U100: =IF(J100="Yes",5,IF(J100="No",1)) -> 1 | V100: =IF(ISBLANK(FeedbackTracker[[#This Row],[Date]]),"",INT(FeedbackTracker[[#This Row],[Date]]-WEEKDAY(FeedbackTracker[[#This Row],[Date]],2)+1)) -> 46006
...

Sheet DUPLICATES
A1: Respondent ID | B1: Date | C1: Venture Name | D1: Mentor Name | E1: Overall Rating (1-5) | F1: How useful was this mentor session for your current business priorities? | G1: Actionability of Advice | H1: Follow-Up Requested? | I1: Verbatim Feedback | J1: Flagged (≤3)? | K1: Action Taken | L1: Response Category | M1: Feedback category | N1: Remarks | O1: Resolved? | P1: Reviewed In Stand-Up? | Q1: # How useful was this mentor session for your current business priorities? | R1: # Actionability of Advice | S1: # Follow-Up Requested? | T1: Date (Week)
A2: 115078086801 | B2: 46125.452 | C2: Zeus Engitech Private Limited | D2: Ankit Majumdar | E2: =AVERAGE(Q2:S2) -> 3 | F2: Moderately useful | G2: Yes | H2: No | I2: I selected “Moderately” because I would like to first implement the insights and suggestions shared, and then evaluate how effective they are. Overall, the session was very good. | J2: =IF(E2<=3,"Yes","No") -> Yes | L2: Duplicate | M2: Duplicate | N2: 13-Apr-2026: The mentor was good, but they wanted to see if the suggestions are truely useful at time of implementation. | Q2: =IF(F2="Extremely useful",5,IF(F2="Very useful",4,IF(F2="Moderately useful",3,IF(F2="Slightly useful",2,IF(F2="Not useful",1))))) -> 3 | R2: =IF(G2="Yes",5,IF(G2="Partly",3,IF(G2="No",1))) -> 5 | S2: =IF(H2="Yes",5,IF(H2="No",1)) -> 1 | T2: =IF(ISBLANK(FeedbackTracker[[#This Row],[Date]]),"",INT(FeedbackTracker[[#This Row],[Date]]-WEEKDAY(FeedbackTracker[[#This Row],[Date]],2)+1)) -> 46160
A3: 115042915820 | B3: 46071.413 | C3: Velaan Mart Pvt Ltd | D3: Ashish Mittal | E3: =AVERAGE(Q3:S3) -> 3.6666667 | F3: Extremely useful | G3: Yes | H3: No | I3: Really good session and we were able to raise funds | J3: =IF(E3<=3,"Yes","No") -> No | M3: Duplicate | Q3: =IF(F3="Extremely useful",5,IF(F3="Very useful",4,IF(F3="Moderately useful",3,IF(F3="Slightly useful",2,IF(F3="Not useful",1))))) -> 5 | R3: =IF(G3="Yes",5,IF(G3="Partly",3,IF(G3="No",1))) -> 5 | S3: =IF(H3="Yes",5,IF(H3="No",1)) -> 1 | T3: =IF(ISBLANK(FeedbackTracker[[#This Row],[Date]]),"",INT(FeedbackTracker[[#This Row],[Date]]-WEEKDAY(FeedbackTracker[[#This Row],[Date]],2)+1)) -> 46153
A4: 115042910595 | B4: 46071.409 | C4: Botminds.ai | D4: Mahesh Nataranjan | E4: =AVERAGE(Q4:S4) -> 3.3333333 | F4: Very useful | G4: Yes | H4: No | J4: =IF(E4<=3,"Yes","No") -> No | K4: Duplicate | L4: Duplicate | M4: Duplicate | N4: Duplicate | Q4: =IF(F4="Extremely useful",5,IF(F4="Very useful",4,IF(F4="Moderately useful",3,IF(F4="Slightly useful",2,IF(F4="Not useful",1))))) -> 4 | R4: =IF(G4="Yes",5,IF(G4="Partly",3,IF(G4="No",1))) -> 5 | S4: =IF(H4="Yes",5,IF(H4="No",1)) -> 1 | T4: =IF(ISBLANK(FeedbackTracker[[#This Row],[Date]]),"",INT(FeedbackTracker[[#This Row],[Date]]-WEEKDAY(FeedbackTracker[[#This Row],[Date]],2)+1)) -> 46153
A5: 115018962266 | B5: 46034.493 | C5: Sarumam Pharmacy | D5: Ajay Rungta | E5: =AVERAGE(Q5:S5) -> 4.3333333 | F5: Moderately useful | G5: Yes | H5: Yes | I5: He was able to identify what I needed and provided the solutions to me immediately. | J5: =IF(E5<=3,"Yes","No") -> No | L5: Received | M5: Duplicate | N5: 31-mar-2026: Required more session with mentor but after april | Q5: =IF(F5="Extremely useful",5,IF(F5="Very useful",4,IF(F5="Moderately useful",3,IF(F5="Slightly useful",2,IF(F5="Not useful",1))))) -> 3 | R5: =IF(G5="Yes",5,IF(G5="Partly",3,IF(G5="No",1))) -> 5 | S5: =IF(H5="Yes",5,IF(H5="No",1)) -> 5 | T5: =IF(ISBLANK(FeedbackTracker[[#This Row],[Date]]),"",INT(FeedbackTracker[[#This Row],[Date]]-WEEKDAY(FeedbackTracker[[#This Row],[Date]],2)+1)) -> 46153
A6: 115016986081 | B6: 46030.403 | C6: Eximburg International | D6: Sriram Chidambaram | E6: =AVERAGE(Q6:S6) -> 3 | F6: Moderately useful | G6: Yes | H6: No | I6: It was meaningful but I want to more about the valuation | J6: =IF(E6<=3,"Yes","No") -> Yes | L6: Duplicate | M6: Duplicate | N6: 31-Mar-206: Time was concern. Limitited time was there for the session | Q6: =IF(F6="Extremely useful",5,IF(F6="Very useful",4,IF(F6="Moderately useful",3,IF(F6="Slightly useful",2,IF(F6="Not useful",1))))) -> 3 | R6: =IF(G6="Yes",5,IF(G6="Partly",3,IF(G6="No",1))) -> 5 | S6: =IF(H6="Yes",5,IF(H6="No",1)) -> 1 | T6: =IF(ISBLANK(FeedbackTracker[[#This Row],[Date]]),"",INT(FeedbackTracker[[#This Row],[Date]]-WEEKDAY(FeedbackTracker[[#This Row],[Date]],2)+1)) -> 46153
A7: 115073800800 | B7: 46118.556 | C7: Eximburg International | D7: Kushagra Gupta | E7: =AVERAGE(Q7:S7) -> 2.3333333 | F7: Moderately useful | G7: Partly | H7: No | I7: Insight of Digital marketing | J7: =IF(E7<=3,"Yes","No") -> Yes | L7: Duplicate | M7: Duplicate | N7: 13-Apr-2026: The mentor was good, but they needed more support in digital marketing. Please suggest another mentor for this. Also, he’d like to connect with Kushagra Gupta for reviewing and auditing my Amazon account. | Q7: =IF(F7="Extremely useful",5,IF(F7="Very useful",4,IF(F7="Moderately useful",3,IF(F7="Slightly useful",2,IF(F7="Not useful",1))))) -> 3 | R7: =IF(G7="Yes",5,IF(G7="Partly",3,IF(G7="No",1))) -> 3 | S7: =IF(H7="Yes",5,IF(H7="No",1)) -> 1 | T7: =IF(ISBLANK(FeedbackTracker[[#This Row],[Date]]),"",INT(FeedbackTracker[[#This Row],[Date]]-WEEKDAY(FeedbackTracker[[#This Row],[Date]],2)+1)) -> 46153
A8: 115063541396 | B8: 46101.677 | C8: Tikitoro | D8: Gaurav Bansal | E8: =AVERAGE(Q8:S8) -> 3.6666667 | F8: Moderately useful | G8: Partly | H8: Yes | I8: The mentor was good and want to meet him even but will fix the agenda and if he agrees that he will be fit for that then only I need a call with him. | J8: =IF(E8<=3,"Yes","No") -> No | K8: Reached out: Response Received | L8: Received | M8: Duplicate | N8: 20-Mar-2026: Will check if the mentor is able give them desired outcome as in if he will agree on the agenda then want another call | Q8: =IF(F8="Extremely useful",5,IF(F8="Very useful",4,IF(F8="Moderately useful",3,IF(F8="Slightly useful",2,IF(F8="Not useful",1))))) -> 3 | R8: =IF(G8="Yes",5,IF(G8="Partly",3,IF(G8="No",1))) -> 3 | S8: =IF(H8="Yes",5,IF(H8="No",1)) -> 5 | T8: =IF(ISBLANK(FeedbackTracker[[#This Row],[Date]]),"",INT(FeedbackTracker[[#This Row],[Date]]-WEEKDAY(FeedbackTracker[[#This Row],[Date]],2)+1)) -> 46153
A9: 115056969460 | B9: 46092.403 | C9: Terrablu | D9: Anant Sood | E9: =AVERAGE(Q9:S9) -> 2.6666667 | F9: Very useful | G9: Partly | H9: No | I9: The session was good. The clearity with which Mr. sood was taking session was beyond imagination. | J9: =IF(E9<=3,"Yes","No") -> Yes | K9: No Response: Call Disconnected | L9: Received | M9: Duplicate | N9: 18-mar-2026: The venture expected immediate advice, but as it was an introductory call, the mentor focused on understanding the venture first. | Q9: =IF(F9="Extremely useful",5,IF(F9="Very useful",4,IF(F9="Moderately useful",3,IF(F9="Slightly useful",2,IF(F9="Not useful",1))))) -> 4 | R9: =IF(G9="Yes",5,IF(G9="Partly",3,IF(G9="No",1))) -> 3 | S9: =IF(H9="Yes",5,IF(H9="No",1)) -> 1 | T9: =IF(ISBLANK(FeedbackTracker[[#This Row],[Date]]),"",INT(FeedbackTracker[[#This Row],[Date]]-WEEKDAY(FeedbackTracker[[#This Row],[Date]],2)+1)) -> 46153
A10: 115042311879 | B10: 46070.693 | C10: Qarmatek | D10: Abhay Jajoo | E10: =AVERAGE(Q10:S10) -> 1 | F10: Not useful | G10: No | H10: No | I10: Not impressed with him | J10: =IF(E10<=3,"Yes","No") -> Yes | L10: Duplicate | M10: Duplicate | N10: Duplicate | Q10: =IF(F10="Extremely useful",5,IF(F10="Very useful",4,IF(F10="Moderately useful",3,IF(F10="Slightly useful",2,IF(F10="Not useful",1))))) -> 1 | R10: =IF(G10="Yes",5,IF(G10="Partly",3,IF(G10="No",1))) -> 1 | S10: =IF(H10="Yes",5,IF(H10="No",1)) -> 1 | T10: =IF(ISBLANK(FeedbackTracker[[#This Row],[Date]]),"",INT(FeedbackTracker[[#This Row],[Date]]-WEEKDAY(FeedbackTracker[[#This Row],[Date]],2)+1)) -> 46153
A11: 115030546274 | B11: 46051.625 | C11: Padcare Labs | D11: Mohanakrishnan P | E11: =AVERAGE(Q11:R11) -> 3 | F11: Moderately useful | G11: Partly | H11: No | J11: =IF(E11<=3,"Yes","No") -> Yes | L11: Duplicate | M11: Filled by Mistake | N11: 17-mar-2026: Venture filled by mistake and was impressed by mentor and is coordinating with the mentor directly for help over email. 16-Mar-2026: Venture rejected the call 11-Mar-2026: Asked to call tomorrow | Q11: =IF(F11="Extremely useful",5,IF(F11="Very useful",4,IF(F11="Moderately useful",3,IF(F11="Slightly useful",2,IF(F11="Not useful",1))))) -> 3 | R11: =IF(G11="Yes",5,IF(G11="Partly",3,IF(G11="No",1))) -> 3 | S11: =IF(H11="Yes",5,IF(H11="No",1)) -> 1 | T11: =IF(ISBLANK(FeedbackTracker[[#This Row],[Date]]),"",INT(FeedbackTracker[[#This Row],[Date]]-WEEKDAY(FeedbackTracker[[#This Row],[Date]],2)+1)) -> 46146
A12: 115023047140 | B12: 46040.427 | C12: Rupiya Finnovations Pvt Ltd | D12: Srinivas Yanamandra | E12: =AVERAGE(Q12:R12) -> 3 | F12: Moderately useful | G12: Partly | H12: Yes | J12: =IF(E12<=3,"Yes","No") -> Yes | L12: Received | M12: 1st Intro Call | N12: 16-Mar-2026: Mentor discussed quality aspects and was a genius guy, and want to connect with mentor again He was also very very helpful . Suggested changes founder is implying also. | Q12: =IF(F12="Extremely useful",5,IF(F12="Very useful",4,IF(F12="Moderately useful",3,IF(F12="Slightly useful",2,IF(F12="Not useful",1))))) -> 3 | R12: =IF(G12="Yes",5,IF(G12="Partly",3,IF(G12="No",1))) -> 3 | S12: =IF(H12="Yes",5,IF(H12="No",1)) -> 5 | T12: =IF(ISBLANK(FeedbackTracker[[#This Row],[Date]]),"",INT(FeedbackTracker[[#This Row],[Date]]-WEEKDAY(FeedbackTracker[[#This Row],[Date]],2)+1)) -> 46146

Sheet SESSION FEEDBACK PIVOT TABLE
A1: Response Category | B1: (Multiple Items)
A3: Row Labels | B3: Count of Venture Name
A4: 46146 | B4: 3
A5: Grand Total | B5: 3

Sheet Quality Dashboard
A1: QUALITY METRICS
A2: Total Sessions Rated | B2: =COUNTA(#REF!) -> 1
A3: Average Rating | B3: =IFERROR(AVERAGE(#REF!),0) -> 0
A4: Sessions Rated ≤ 3 (Negative) | B4: =COUNTIF(FeedbackTracker[Overall Rating (1-5)],"<=3") -> 26
A5: Sessions Rated 4-5 (Positive) | B5: =COUNTIF(FeedbackTracker[Overall Rating (1-5)],">=4") -> 70
A6: % Positive Sessions | B6: =IFERROR(B6/(B3),0) -> 0
A7: Follow-Up Requests | B7: =COUNTIF(FeedbackTracker[Follow-Up Requested?],"Yes") -> 31
A8: Flagged & Unresolved | B8: =COUNTIFS(FeedbackTracker[Flagged (≤3)?],"Yes",FeedbackTracker[Resolved?],"No") -> 0
A10: MENTOR QUALITY FLAGS
A11: (Track mentors with 3+ negative ratings for reassignment review)

Sheet Feedback from Mentor
A1: Respondent ID | B1: Collector ID | C1: Start Date | D1: End Date | E1: IP Address | F1: Email Address | G1: First Name | H1: Last Name | I1: Custom Data 1 | J1: Your Name | K1: Venture Name | L1: Mentee Name | M1: 1. Was the session agenda relevant to the startup’s current stage and specific needs? | N1: 2. Did the session agenda help you prepare effectively for the discussion? | O1: 3. Was the startup’s problem statement or request clearly articulated in the agenda? | P1: 4. Do you have any suggestions to improve the quality or format of the agenda or recommendations? | Q1: 5. How prepared and organized was your mentee for the session? | R1: 6. How engaged is your mentee during mentoring sessions, in terms of active participation and willingness to discuss challenges? | S1: 7. Is there anything the venture (or platform) could have done better to make this session more effective? | T1: 8. How would you like to rate the session? | U1: 9. How relevant were the recommended action items to the discussion during your session? | V1: 10. Were the suggested resources and tools aligned with the session topic and helpful for your next steps? | W1: 11. Is there any additional critical information you believe should be included in the post-session recommendations? | X1: RN Remarks | Y1: Category | Z1: Response Status | AA1: Start of Week | AB1: Trunc
A2: 115078155867 | B2: 438983145 | C2: 46125.606 | D2: 46125.609 | E2: 114.143.38.219 | J2: Garima Mitra | K2: Keepsake Automation Pvt Ltd | L2: Keepsake Automation | M2: Moderately Relevant | N2: Slightly helpful | O2: Not at all articulated | P2: Agenda has to be articulated. | Q2: Highly prepared | R2: Highly Engaged | S2: Set the Agenda. | T2: Neutral | U2: Moderately Relevant | V2: Moderately aligned | AA2: =IF(ISBLANK(FeedbackFrmMentor[[#This Row],[Start Date]]),"",FeedbackFrmMentor[[#This Row],[Start Date]]-WEEKDAY(FeedbackFrmMentor[[#This Row],[Start Date]],2)+1) -> 46125.606 | AB2: =TRUNC(FeedbackFrmMentor[[#This Row],[Start of Week]],0) -> 46125
A3: 115076821481 | B3: 438983145 | C3: 46122.53 | D3: 46122.531 | E3: 42.105.172.191 | J3: Ankit Majmudar | K3: Zeus Engitech Private Limited | L3: Delzad Khambata | M3: Extremely Relevant | N3: Extremely helpful | O3: Clearly articulated | P3: All was good | AA3: =IF(ISBLANK(FeedbackFrmMentor[[#This Row],[Start Date]]),"",FeedbackFrmMentor[[#This Row],[Start Date]]-WEEKDAY(FeedbackFrmMentor[[#This Row],[Start Date]],2)+1) -> 46118.53 | AB3: =TRUNC(FeedbackFrmMentor[[#This Row],[Start of Week]],0) -> 46118
A4: 115074566802 | B4: 438983145 | C4: 46119.659 | D4: 46119.66 | E4: 183.83.219.29 | J4: Kushagra Gupta | K4: Eximburg International | L4: Hitesh | M4: Moderately Relevant | N4: Moderately helpful | O4: Moderately articulated | Q4: Moderately prepared | R4: Somewhat Engaged | T4: Neutral | U4: Moderately Relevant | V4: Moderately aligned | AA4: =IF(ISBLANK(FeedbackFrmMentor[[#This Row],[Start Date]]),"",FeedbackFrmMentor[[#This Row],[Start Date]]-WEEKDAY(FeedbackFrmMentor[[#This Row],[Start Date]],2)+1) -> 46118.659 | AB4: =TRUNC(FeedbackFrmMentor[[#This Row],[Start of Week]],0) -> 46118
A5: 115068064794 | B5: 438983145 | C5: 46108.442 | D5: 46108.444 | E5: 122.172.82.128 | J5: Shridhar N Upadhye | K5: Tikitaro | L5: Prasanna Vasanadu | M5: Extremely Relevant | N5: Extremely helpful | O5: Exceptionally well-defined | P5: NIL | Q5: Extremely prepared | R5: Extremely Engaged | S5: NIL | T5: Very satisfied | U5: Extremely Relevant | V5: Extremely aligned | W5: NIL | AA5: =IF(ISBLANK(FeedbackFrmMentor[[#This Row],[Start Date]]),"",FeedbackFrmMentor[[#This Row],[Start Date]]-WEEKDAY(FeedbackFrmMentor[[#This Row],[Start Date]],2)+1) -> 46104.442 | AB5: =TRUNC(FeedbackFrmMentor[[#This Row],[Start of Week]],0) -> 46104
A6: 115067614145 | B6: 438983145 | C6: 46107.871 | D6: 46107.872 | E6: 106.219.225.66 | J6: Krishna Dorai | K6: Tikitaro | L6: Nagaprasanna | M6: Extremely Relevant | N6: Extremely helpful | O6: Exceptionally well-defined | Q6: Extremely prepared | R6: Extremely Engaged | T6: Very satisfied | U6: Very Relevant | V6: Extremely aligned | AA6: =IF(ISBLANK(FeedbackFrmMentor[[#This Row],[Start Date]]),"",FeedbackFrmMentor[[#This Row],[Start Date]]-WEEKDAY(FeedbackFrmMentor[[#This Row],[Start Date]],2)+1) -> 46104.871 | AB6: =TRUNC(FeedbackFrmMentor[[#This Row],[Start of Week]],0) -> 46104
A7: 115063561843 | B7: 438983145 | C7: 46101.726 | D7: 46101.728 | E7: 49.36.221.62 | J7: Gaurav Bansal | K7: Tikitaro | L7: Nagaprasanna Vasanadu | M7: Extremely Relevant | N7: Extremely helpful | O7: Clearly articulated | P7: None as of now, good initiative, keep rocking !!! | Q7: Highly prepared | R7: Extremely Engaged | S7: none as of now, stick to the current format, its working fine !! | T7: Very satisfied | U7: Extremely Relevant | V7: Extremely aligned | W7: None as of now | AA7: =IF(ISBLANK(FeedbackFrmMentor[[#This Row],[Start Date]]),"",FeedbackFrmMentor[[#This Row],[Start Date]]-WEEKDAY(FeedbackFrmMentor[[#This Row],[Start Date]],2)+1) -> 46097.726 | AB7: =TRUNC(FeedbackFrmMentor[[#This Row],[Start of Week]],0) -> 46097
A8: 115062975290 | B8: 438983145 | C8: 46100.832 | D8: 46100.837 | E8: 223.231.165.162 | J8: Shridhar N Upadhye | K8: Tikitaro | L8: Prasanna Vasanadu | M8: Extremely Relevant | N8: Extremely helpful | O8: Exceptionally well-defined | P8: Nothing as of now | Q8: Extremely prepared | R8: Extremely Engaged | S8: Nothing specific | T8: Very satisfied | U8: Extremely Relevant | V8: Extremely aligned | W8: Nothing specific | AA8: =IF(ISBLANK(FeedbackFrmMentor[[#This Row],[Start Date]]),"",FeedbackFrmMentor[[#This Row],[Start Date]]-WEEKDAY(FeedbackFrmMentor[[#This Row],[Start Date]],2)+1) -> 46097.832 | AB8: =TRUNC(FeedbackFrmMentor[[#This Row],[Start of Week]],0) -> 46097
A9: 115061108178 | B9: 438983145 | C9: 46098.418 | D9: 46098.429 | E9: 106.202.63.28 | J9: Shailendrasinh Rajput | K9: Bull AgriTech | L9: Divyajit | M9: Highly Relevant | N9: Moderately helpful | O9: Clearly articulated | P9: After introductory session i believe it should now in execution type and action oriented. | Q9: Extremely prepared | R9: Extremely Engaged | S9: Share more detail problems which understand not possible in one session | T9: Very satisfied | U9: Very Relevant | V9: Extremely aligned | W9: we should be clear what next action we be taking to improve the need of venture and how to go about with team work | AA9: =IF(ISBLANK(FeedbackFrmMentor[[#This Row],[Start Date]]),"",FeedbackFrmMentor[[#This Row],[Start Date]]-WEEKDAY(FeedbackFrmMentor[[#This Row],[Start Date]],2)+1) -> 46097.418 | AB9: =TRUNC(FeedbackFrmMentor[[#This Row],[Start of Week]],0) -> 46097
A10: 115060504360 | B10: 438983145 | C10: 46097.716 | D10: 46097.72 | E10: 171.76.80.255 | J10: Sivesh Kumar | K10: Bebe Burp | L10: Forgot | M10: Highly Relevant | N10: Very helpful | O10: Clearly articulated | P10: I guess it was ok, and not much is required. | Q10: Extremely prepared | R10: Highly Engaged | S10: It is not a one-time thing; mentorship requires more time than just a session. You should work more on it. Assigning mentees for longer periods with a mentor | T10: Satisfied | U10: Very Relevant | V10: Very aligned | W10: The mentee was looking more on the side of fundrasing than strategic support. He was a bit confused with GTM but mainly fundraising. It should be clear what the acceptance of mentee is, before entering the call. | AA10: =IF(ISBLANK(FeedbackFrmMentor[[#This Row],[Start Date]]),"",FeedbackFrmMentor[[#This Row],[Start Date]]-WEEKDAY(FeedbackFrmMentor[[#This Row],[Start Date]],2)+1) -> 46097.716 | AB10: =TRUNC(FeedbackFrmMentor[[#This Row],[Start of Week]],0) -> 46097
A11: 115060464576 | B11: 438983145 | C11: 46097.654 | D11: 46097.655 | E11: 122.166.190.164 | J11: Bharat Hudadalli | K11: Bebe Burp | L11: Chirag Gupta & Bharat Tiberwel | M11: Highly Relevant | N11: Extremely helpful | O11: Clearly articulated | P11: All good | Q11: Highly prepared | R11: Highly Engaged | S11: All good | T11: Satisfied | U11: Very Relevant | V11: Very aligned | W11: N/A | AA11: =IF(ISBLANK(FeedbackFrmMentor[[#This Row],[Start Date]]),"",FeedbackFrmMentor[[#This Row],[Start Date]]-WEEKDAY(FeedbackFrmMentor[[#This Row],[Start Date]],2)+1) -> 46097.654 | AB11: =TRUNC(FeedbackFrmMentor[[#This Row],[Start of Week]],0) -> 46097
A12: 115055433189 | B12: 438983145 | C12: 46090.623 | D12: 46090.625 | E12: 1.7.46.162 | J12: Bharat Hudadalli | K12: Bebe Burp | L12: Chirag Gupta & Bharat Tiberwal | M12: Extremely Relevant | N12: Very helpful | O12: Clearly articulated | P12: So far good! | Q12: Highly prepared | R12: Extremely Engaged | S12: All good! | T12: Very satisfied | U12: Very Relevant | V12: Extremely aligned | AA12: =IF(ISBLANK(FeedbackFrmMentor[[#This Row],[Start Date]]),"",FeedbackFrmMentor[[#This Row],[Start Date]]-WEEKDAY(FeedbackFrmMentor[[#This Row],[Start Date]],2)+1) -> 46090.623 | AB12: =TRUNC(FeedbackFrmMentor[[#This Row],[Start of Week]],0) -> 46090
C13: 46072.643 | J13: Jignesh Jain | K13: JustAct | L13: Rahul | M13: Moderately Relevant | N13: Moderately helpful | O13: Clearly articulated | AA13: =IF(ISBLANK(FeedbackFrmMentor[[#This Row],[Start Date]]),"",FeedbackFrmMentor[[#This Row],[Start Date]]-WEEKDAY(FeedbackFrmMentor[[#This Row],[Start Date]],2)+1) -> 46069.643 | AB13: =TRUNC(FeedbackFrmMentor[[#This Row],[Start of Week]],0) -> 46069
C14: 46072.65 | J14: Vignesh Narayanan | K14: Ask EVA | L14: Mohammad eshan | M14: Moderately Relevant | N14: Slightly helpful | O14: Not at all articulated | AA14: =IF(ISBLANK(FeedbackFrmMentor[[#This Row],[Start Date]]),"",FeedbackFrmMentor[[#This Row],[Start Date]]-WEEKDAY(FeedbackFrmMentor[[#This Row],[Start Date]],2)+1) -> 46069.65 | AB14: =TRUNC(FeedbackFrmMentor[[#This Row],[Start of Week]],0) -> 46069
C15: 46072.659 | J15: Dr. Naman Agarwal | K15: Leap Info | L15: Sudhir | M15: Extremely Relevant | N15: Extremely helpful | O15: Exceptionally well-defined | AA15: =IF(ISBLANK(FeedbackFrmMentor[[#This Row],[Start Date]]),"",FeedbackFrmMentor[[#This Row],[Start Date]]-WEEKDAY(FeedbackFrmMentor[[#This Row],[Start Date]],2)+1) -> 46069.659 | AB15: =TRUNC(FeedbackFrmMentor[[#This Row],[Start of Week]],0) -> 46069
C16: 46072.678 | J16: Abhay Jajoo | K16: Qarmatek | L16: Krunal Shah | M16: Moderately Relevant | N16: Moderately helpful | O16: Moderately articulated | AA16: =IF(ISBLANK(FeedbackFrmMentor[[#This Row],[Start Date]]),"",FeedbackFrmMentor[[#This Row],[Start Date]]-WEEKDAY(FeedbackFrmMentor[[#This Row],[Start Date]],2)+1) -> 46069.678 | AB16: =TRUNC(FeedbackFrmMentor[[#This Row],[Start of Week]],0) -> 46069
C17: 46072.683 | J17: Suhasini Barman | K17: REAGRI - NANOBEE BIOINNOVATIONS | L17: Reagri | M17: Extremely Relevant | N17: Extremely helpful | O17: Clearly articulated | AA17: =IF(ISBLANK(FeedbackFrmMentor[[#This Row],[Start Date]]),"",FeedbackFrmMentor[[#This Row],[Start Date]]-WEEKDAY(FeedbackFrmMentor[[#This Row],[Start Date]],2)+1) -> 46069.683 | AB17: =TRUNC(FeedbackFrmMentor[[#This Row],[Start of Week]],0) -> 46069
C18: 46072.746 | J18: Abhay Jajoo | K18: Servercake | L18: Amith Kumar Kalimuthu | M18: Extremely Relevant | N18: Extremely helpful | O18: Exceptionally well-defined | AA18: =IF(ISBLANK(FeedbackFrmMentor[[#This Row],[Start Date]]),"",FeedbackFrmMentor[[#This Row],[Start Date]]-WEEKDAY(FeedbackFrmMentor[[#This Row],[Start Date]],2)+1) -> 46069.746 | AB18: =TRUNC(FeedbackFrmMentor[[#This Row],[Start of Week]],0) -> 46069
C19: 46072.768 | J19: Ashesh D Shah | K19: Qarmatek | L19: Krunal Shah | M19: Extremely Relevant | N19: Extremely helpful | O19: Exceptionally well-defined | AA19: =IF(ISBLANK(FeedbackFrmMentor[[#This Row],[Start Date]]),"",FeedbackFrmMentor[[#This Row],[Start Date]]-WEEKDAY(FeedbackFrmMentor[[#This Row],[Start Date]],2)+1) -> 46069.768 | AB19: =TRUNC(FeedbackFrmMentor[[#This Row],[Start of Week]],0) -> 46069
C20: 46072.769 | J20: Nirmallya Roy Chowdhury | K20: Qarmatek | L20: Krunal Shah | M20: Extremely Relevant | N20: Extremely helpful | O20: Exceptionally well-defined | AA20: =IF(ISBLANK(FeedbackFrmMentor[[#This Row],[Start Date]]),"",FeedbackFrmMentor[[#This Row],[Start Date]]-WEEKDAY(FeedbackFrmMentor[[#This Row],[Start Date]],2)+1) -> 46069.769 | AB20: =TRUNC(FeedbackFrmMentor[[#This Row],[Start of Week]],0) -> 46069
C21: 46072.781 | J21: Deepak Srinivasan | K21: Vaultastic | L21: Tarun | M21: Highly Relevant | N21: Very helpful | O21: Clearly articulated | AA21: =IF(ISBLANK(FeedbackFrmMentor[[#This Row],[Start Date]]),"",FeedbackFrmMentor[[#This Row],[Start Date]]-WEEKDAY(FeedbackFrmMentor[[#This Row],[Start Date]],2)+1) -> 46069.781 | AB21: =TRUNC(FeedbackFrmMentor[[#This Row],[Start of Week]],0) -> 46069
C22: 46072.802 | J22: Srinivas Yanamandra | K22: Rupiya Finnovations Pvt Ltd | L22: Dhaval shah | M22: Extremely Relevant | N22: Extremely helpful | O22: Exceptionally well-defined | AA22: =IF(ISBLANK(FeedbackFrmMentor[[#This Row],[Start Date]]),"",FeedbackFrmMentor[[#This Row],[Start Date]]-WEEKDAY(FeedbackFrmMentor[[#This Row],[Start Date]],2)+1) -> 46069.802 | AB22: =TRUNC(FeedbackFrmMentor[[#This Row],[Start of Week]],0) -> 46069
C23: 46072.808 | J23: Srinivas Yanamandra | K23: Hreedan Lifestyle | L23: Rekharani bhanudas mane | M23: Extremely Relevant | N23: Extremely helpful | O23: Exceptionally well-defined | AA23: =IF(ISBLANK(FeedbackFrmMentor[[#This Row],[Start Date]]),"",FeedbackFrmMentor[[#This Row],[Start Date]]-WEEKDAY(FeedbackFrmMentor[[#This Row],[Start Date]],2)+1) -> 46069.808 | AB23: =TRUNC(FeedbackFrmMentor[[#This Row],[Start of Week]],0) -> 46069
C24: 46072.81 | J24: Kavya Dehulia | K24: Stembotix | L24: Sagar | M24: Not Relevant | N24: Not at all helpful | O24: Not at all articulated | AA24: =IF(ISBLANK(FeedbackFrmMentor[[#This Row],[Start Date]]),"",FeedbackFrmMentor[[#This Row],[Start Date]]-WEEKDAY(FeedbackFrmMentor[[#This Row],[Start Date]],2)+1) -> 46069.81 | AB24: =TRUNC(FeedbackFrmMentor[[#This Row],[Start of Week]],0) -> 46069
... C32: 46073.411 | J32: Manu Kumar | K32: Raptee Energy Pvt Ltd | L32: Dinesh Arjun | M32: Highly Relevant | N32: Extremely helpful | O32: Exceptionally well-defined | AA32: =IF(ISBLANK(FeedbackFrmMentor[[#This Row],[Start Date]]),"",FeedbackFrmMentor[[#This Row],[Start Date]]-WEEKDAY(FeedbackFrmMentor[[#This Row],[Start Date]],2)+1) -> 46069.411 | AB32: =TRUNC(FeedbackFrmMentor[[#This Row],[Start of Week]],0) -> 46069

Sheet Feedback from Mentor Pivot 
A1: Trunc | B1: Count of Venture Name
A2: 46069 | B2: 20
A3: 46090 | B3: 1
A4: 46097 | B4: 5
A5: 46104 | B5: 2
A6: 46118 | B6: 2
A7: 46125 | B7: 1
A8: Grand Total | B8: 31

Sheet NPS Calculation
A2: Feedback from Founders | B2: # | E2: Mentor Workbench NPS | F2: #
A3: Not useful | B3: =COUNTIFS(FeedbackTracker[How useful was this mentor session for your current business priorities?],'NPS Calculation'!A3,FeedbackTracker[Response Category],"<>Duplicate") -> 2 | E3: Not Relevant | F3: =COUNTIFS(FeedbackFrmMentor[1. Was the session agenda relevant to the startup’s current stage and specific needs?],'NPS Calculation'!E3) -> 1
A4: Slightly useful | B4: =COUNTIFS(FeedbackTracker[How useful was this mentor session for your current business priorities?],'NPS Calculation'!A4,FeedbackTracker[Response Category],"<>Duplicate") -> 7 | E4: Slightly Relevant | F4: =COUNTIFS(FeedbackFrmMentor[1. Was the session agenda relevant to the startup’s current stage and specific needs?],'NPS Calculation'!E4) -> 0
A5: Moderately useful | B5: =COUNTIFS(FeedbackTracker[How useful was this mentor session for your current business priorities?],'NPS Calculation'!A5,FeedbackTracker[Response Category],"<>Duplicate") -> 21 | E5: Moderately Relevant | F5: =COUNTIFS(FeedbackFrmMentor[1. Was the session agenda relevant to the startup’s current stage and specific needs?],'NPS Calculation'!E5) -> 5
A6: Very useful | B6: =COUNTIFS(FeedbackTracker[How useful was this mentor session for your current business priorities?],'NPS Calculation'!A6,FeedbackTracker[Response Category],"<>Duplicate") -> 54 | E6: Highly Relevant | F6: =COUNTIFS(FeedbackFrmMentor[1. Was the session agenda relevant to the startup’s current stage and specific needs?],'NPS Calculation'!E6) -> 6
A7: Extremely useful | B7: =COUNTIFS(FeedbackTracker[How useful was this mentor session for your current business priorities?],'NPS Calculation'!A7,FeedbackTracker[Response Category],"<>Duplicate") -> 22 | E7: Extremely Relevant | F7: =COUNTIFS(FeedbackFrmMentor[1. Was the session agenda relevant to the startup’s current stage and specific needs?],'NPS Calculation'!E7) -> 19
A8: SUM | B8: =SUM(B3:B7) -> 106 | E8: SUM | F8: =SUM(F3:F7) -> 31
A10: Promoter | B10: =B6+B7 -> 76 | E10: Promoter | F10: =F6+F7 -> 25
A11: Passive | B11: =B5+B4 -> 28 | E11: Passive | F11: =F5+F4 -> 5
A12: Detractor | B12: =B3 -> 2 | E12: Detractor | F12: =F3 -> 1
A14: NPS | B14: =((B10-B12)/B8)*100 -> 69.811321 | E14: NPS | F14: =((F10-F12)/F8)*100 -> 77.419355
A18: Promoter | B18: 46 | C18: 78
A19: Passive | B19: 37 | C19: 11
A20: Detractor | B20: 14 | C20: 8
A22: NPS | B22: =((B18-B20)/SUM(B18:B20))*100 -> 32.989691 | C22: =((C18-C20)/SUM(C18:C20))*100 -> 72.164948
